{
  "Catar": {
    "grupo": "A",
    "Nome": "do Catar",
    "Treinador": "Félix Sánchez",
    "flag": "assets/images/GrupoA/catar/catar.png",
    "0": [
      "22",
      "Meshaal Barsham",
      "Goleiro",
      "24",
      "Al-Sadd SC"
    ],
    "1": [
      "1",
      "Saad Al-Sheeb",
      "Goleiro",
      "32",
      "Al-Sadd SC"
    ],
    "2": [
      "21",
      "Yousef Hassan",
      "Goleiro",
      "25",
      "Al-Gharafa SC"
    ],
    "3": [
      "2",
      "Pedro Miguel",
      "Zagueiro",
      "31",
      "Al-Sadd SC"
    ],
    "4": [
      "5",
      "Tarek Salman",
      "Zagueiro",
      "31",
      "Al-Sadd SC"
    ],
    "5": [
      "15",
      "Bassam Al-Rawi",
      "Zagueiro",
      "24",
      "Al-Duhail SC"
    ],
    "6": [
      "16",
      "Boualem Khoukhi",
      "Zagueiro",
      "31",
      "Al-Sadd SC"
    ],
    "7": [
      "3",
      "Abdelkarim Hassan",
      "Lateral Esq.",
      "28",
      "Al-Sadd SC"
    ],
    "8": [
      "14",
      "Homam Ahmed",
      "Lateral Esq.",
      "22",
      "Al-Gharafa SC"
    ],
    "9": [
      "13",
      "Musab Khoder",
      "Lateral Dir.",
      "29",
      "Al-Sadd SC"
    ],
    "10": [
      "12",
      "Karim Boudiaf",
      "Volante",
      "31",
      "Al-Duhail SC"
    ],
    "11": [
      "23",
      "Assim Madibo",
      "Volante",
      "25",
      "Al-Duhail SC"
    ],
    "12": [
      "4",
      "Mohammed Waad",
      "Meia Central",
      "22",
      "Al-Sadd SC"
    ],
    "13":  [
      "20",
      "Abdullah Al-Ahrak",
      "Meia Ofensivo",
      "24",
      "Al-Arabi SC"
    ],
    "14": [
      "8",
      "Ali Asad",
      "Meia Ofensivo",
      "29",
      "Al-Sadd SC"
    ],
    "15": [
      "11",
      "Akram Afif",
      "Ponta Esq.",
      "25",
      "Al-Sadd SC"
    ],
    "16": [
      "-",
      "Abdelrahman Moustafa",
      "Ponta Esquerda",
      "25",
      "Al-Arabi SC"
    ],
    "17": [
      "18",
      "Khalid Muneer Mazeed",
      "Ponta Esquerda",
      "24",
      "Al-Wakrah SC"
    ],
    "18": [
      "-",
      "Hazem Ahmed",
      "Ponta Direita",
      "24",
      "Al-Wakrah SC"
    ],
    "19": [
      "17",
      "Ismaeel Mohammed",
      "Ponta Direita",
      "32",
      "Al-Arabi SC"
    ],
    "20": [
      "-",
      "Naif Al-Hadhrami",
      "Ponta Direita",
      "20",
      "Al-Rayyan SC"
    ],
    "21": [
      "19",
      "Almoez Ali",
      "Centroavante",
      "25",
      "Al-Duhail SC"
    ],
    "22": [
      "7",
      "Meshaal Barsham",
      "Goleiro",
      "24",
      "Al-Sadd SC"
    ],
    "23": [
      "22",
      "Ahmed Alaaeldin",
      "Centroavante",
      "29",
      "Al-Gharafa SC"
    ]
  },
  "Equador": {
      "grupo": "A",
      "Nome": "do Equador",
      "Treinador": "Gustavo Alfaro",
      "flag": "assets/images/GrupoA/equador/equador.png",
      "0": [
          "22",
          "Moisés Ramírez",
          "Goleiro",
          "21",
          "Independiente del Valle"
      ],
      "1": [
          "1",
          "Hernán Galíndez",
          "Goleiro",
          "35",
          "CF Universidad de Chile"
      ],
      "2": [
          "12",
          "Jorge Pinos",
          "Goleiro",
          "32",
          "AD Nueve de Octubre"
      ],
      "3": [
          "33",
          "Piero Hincapié",
          "Zagueiro",
          "20",
          "AD Nueve de Octubre"
      ],
      "4": [
          "2",
          "Félix Torres",
          "Zagueiro",
          "25",
          "San Lorenzo"
      ],
      "5": [
          "4",
          "Robert Arboleda",
          "Zagueiro",
          "30",
          "São Paulo FC"
      ],
      "6": [
          "30",
          "Fernando León",
          "Zagueiro",
          "29",
          "Valencia"
      ],
      "7": [
          "14",
          "Xavier Arreaga",
          "Zagueiro",
          "27",
          "Seattle Sounders FC"
      ],
      "8": [
          "7",
          "Pervis Estupiñán",
          "Lateral Esq.",
          "24",
          "FC Villarreal"
      ],
      "9": [
          "18",
          "Diego Palacios",
          "Lateral Esq.",
          "22",
          "Los Angeles FC"
      ],
      "10": [
          "6",
          "Byron Castillo",
          "Lateral Dir.",
          "23",
          "Barcelona SC"
      ],
      "11": [
          "17",
          "Angelo Preciado",
          "Lateral Dir.",
          "24",
          "KRC Genk"
      ],
      "12": [
          "8",
          "Carlos Gruezo",
          "Volante",
          "27",
          "Augsburgo FC"
      ],
      "13": [
          "20",
          "Jhegson Méndez",
          "Volante",
          "25",
          "Orlando City SC"
      ],
      "14": [
          "5",
          "Michael Carcelén",
          "Volante",
          "25",
          "Barcelona SC"
      ],
      "15": [
          "21",
          "José Cifuentes",
          "Meia Central",
          "23",
          "Los Angeles FC"
      ],
      "16": [
          "23",
          "Moisés Caicedo",
          "Meia Central",
          "20",
          "Brighton Albion"
      ],
      "17": [
          "21",
          "Alan Franco",
          "Meia Central",
          "23",
          "Charlotte FC"
      ],
      "18": [
          "-",
          "Danny Cabezas",
          "Meia Ofensivo",
          "29",
          "Independiente del Valle"
      ],
      "19": [
          "16",
          "Jeremy Sarmiento",
          "Meia Ofensivo",
          "19",
          "Brighton Albion"
      ],
      "20": [
          "10",
          "Joao Rojas",
          "Ponta Esquerda",
          "24",
          "CS Emelec"
      ],
      "21": [
          "10",
          "Romario Ibarra",
          "Ponta Esquerda",
          "27",
          "CF Pachuca"
      ],
      "22": [
          "19",
          "Gonzalo Plata",
          "Ponta Direita",
          "21",
          "Real Valladolid CF"
      ],
      "23": [
          "15",
          "Ángel Mena",
          "Ponta Direita",
          "34",
          "Club León"
      ],
      "24": [
          "11",
          "Michael Estrada",
          "Centroavante",
          "26",
          "D.C. United"
      ],
      "25": [
          "13",
          "Enner Valencia",
          "Centroavante",
          "32",
          "Fenerbahce SK"
      ],
      "26": [
          "9",
          "Jordy Caicedo",
          "Centroavante",
          "24",
          "CSKA-Sofia"
      ],
      "27": [
          "16",
          "Djorkaeff Reasco",
          "Centroavante",
          "23",
          "CA Newell's Old Boys"
      ]
  },
  "Senegal": {
    "grupo": "A",
    "Nome": "do Senal",
    "Treinador": "Treinador do Senegal",
    "flag": "assets/images/GrupoA/senegal/senegal.png",
    "0": [
      "16",
      "Edouard Mendy",
      "Goleiro",
      "30",
      "Chelsea FC"
    ],
    "1": [
        "1",
        "Bingourou Kamara",
        "Goleiro",
        "25",
        "RSC Charleroi"
    ],
    "2": [
        "28",
        "Aliou Badara Faty",
        "Goleiro",
        "23",
        "Casa Sports"
    ],
    "3": [
        "26",
        "Kalidou Koulibaly",
        "Zagueiro",
        "30",
        "Nápoles"
    ],
    "4": [
        "4",
        "Pape Abou Cissé",
        "Zagueiro",
        "26",
        "Olympiacos Pireu"
    ],
    "5": [
        "14",
        "Abdoulaye Seck",
        "Zagueiro",
        "29",
        "Royal Antuérpia FC"
    ],
    "6": [
        "22",
        "Abdou Diallo",
        "Lateral Esq.",
        "26",
        "Paris Saint-German FC"
    ],
    "7": [
        "12",
        "Fodé Ballo-Touré",
        "Lateral Esq.",
        "25",
        "AC Milan"
    ],
    "8": [
        "2",
        "Saliou Ciss",
        "Lateral Esq.",
        "32",
        "AS Nancy-Lorraine"
    ],
    "9": [
        "-",
        "Youssouf Sabaly",
        "Lateral Dir.",
        "29",
        "Real Bétis"
    ],
    "10": [
        "20",
        "Bouna Sarr",
        "Lateral Dir.",
        "30",
        "FC Bayern de Munique"
    ],
    "11": [
        "17",
        "Pape Sarr",
        "Volante",
        "19",
        "FC Metz"
    ],
    "12": [
        "-",
        "Idrissa Gueye",
        "Volante",
        "29",
        "FC Paris Saint-Germain"
    ],
    "13": [
        "6",
        "Nampalys Mendy",
        "Volante",
        "29",
        "Leicester City FC"
    ],
    "14": [
        "22",
        "Pape Gueye",
        "Volante",
        "23",
        "Olympique Marselha"
    ],
    "15": [
        "8",
        "Cheikhou Kouyaté",
        "Volante",
        "32",
        "Crystal Palace FC"
    ],
    "16": [
        "25",
        "Mamadou Loum",
        "Volante",
        "25",
        "Deportivo Alavés"
    ],
    "17": [
        "24",
        "Moustapha Name",
        "Meia Central",
        "27",
        "Paris FC"
    ],
    "18": [
        "10",
        "Sadio Mané",
        "Ponta Esq.",
        "30",
        "FC Liverpool"
    ],
    "19": [
        "27",
        "Mame Thiam",
        "Ponta Esq.",
        "29",
        "Kayserispor"
    ],
    "20": [
        "18",
        "Ismaïla Sarr",
        "Ponta Dir.",
        "24",
        "FC Watford"
    ],
    "21": [
        "9",
        "Boulaye Dia",
        "Centroavante",
        "25",
        "FC Watford"
    ],
    "22": [
        "11",
        "Habib Diallo",
        "Centroavante",
        "26",
        "RC Strasbourg Alsace"
    ],
    "23": [
        "15",
        "Bamba Dieng",
        "Centroavante",
        "22",
        "Olympique Marselha"
    ],
    "24": [
        "7",
        "Keita Baldé",
        "Centroavante",
        "27",
        "Cagliari Calcio"
    ],
    "25": [
        "19",
        "Famara Diédhiou",
        "Centroavante",
        "29",
        "Alanyaspor"
    ]
  },
  "Holanda": {
    "grupo": "A",
    "Nome": "da Holanda",
    "Treinador": "Louis van Gaal",
    "flag": "assets/images/GrupoA/holanda/holanda.png",
    "0": [
        "1",
        "Mark Flekken",
        "Goleiro",
        "28",
        "SC Freiburg"
    ],
    "1": [
        "23",
        "Joël Drommel",
        "Goleiro",
        "25",
        "PSV Eindhoven"
    ],
    "2": [
        "13",
        "Tim Krul",
        "Goleiro",
        "34",
        "Norwich City"
    ],
    "3": [
        "3",
        "Matthijs de Ligt",
        "Zagueiro",
        "22",
        "Juventus FC"
    ],
    "4": [
        "4",
        "Virgil van Dijk",
        "Zagueiro",
        "30",
        "FC Liverpool"
    ],
    "5": [
        "5",
        "Nathan Aké",
        "Zagueiro",
        "27",
        "Manchester City FC"
    ],
    "6": [
        "12",
        "Owen Wijndal",
        "Lateral Esq.",
        "22",
        "AZ Alkmaar"
    ],
    "7": [
        "6",
        "Tyrell Malacia",
        "Lateral Esq.",
        "22",
        "Feyenoord"
    ],
    "8": [
        "17",
        "Daley Blind",
        "Lateral Esq.",
        "32",
        "AFC Ajax"
    ],
    "9": [
        "2",
        "Hans Hateboer",
        "Lateral Dir.",
        "28",
        "Atalanta BC"
    ],
    "10": [
        "20",
        "Teun Koopmeiners",
        "Volante",
        "24",
        "Atalanta BC"
    ],
    "11": [
        "15",
        "Marten de Roon",
        "Volante",
        "31",
        "Atalanta BC"
    ],
    "12": [
        "16",
        "Jordy Clasie",
        "Volante",
        "30",
        "AZ Alkmaar"
    ],
    "13": [
        "21",
        "Frenkie de Jong",
        "Volante",
        "24",
        "Barcelona FC"
    ],
    "14": [
        "8",
        "Georginio Wijnaldum",
        "Meia Central",
        "31",
        "FC Paris Saint-Germain"
    ],
    "15": [
        "22",
        "Denzel Dumfries",
        "Meia Dir.",
        "26",
        "Inter de Milão"
    ],
    "16": [
        "14",
        "Davy Klaassen",
        "Meia Ofensivo",
        "29",
        "AFC Ajax"
    ],
    "17": [
        "-",
        "Guus Til",
        "Meia Ofensivo",
        "24",
        "Feyenoord"
    ],
    "18": [
        "9",
        "Arnaut Danjuma",
        "Ponta Esq.",
        "25",
        "FC Villarreal"
    ],
    "19": [
        "--",
        "Noa Lang",
        "Ponta Esq.",
        "22",
        "Club Brugge"
    ],
    "20": [
        "7",
        "Steven Bergwijn",
        "Ponta Esq.",
        "24",
        "Tottenham Hotspur"
    ],
    "21": [
        "11",
        "Steven Berghuis",
        "Ponta Dir.",
        "30",
        "AFC Ajax"
    ],
    "22": [
        "10",
        "Memphis Depay",
        "Centroavante",
        "28",
        "FC Barcelona"
    ],
    "23": [
        "18",
        "Donyell Malen",
        "Centroavante",
        "23",
        "Borussia Dortmund"
    ],
    "24": [
        "19",
        "Wout Weghorst",
        "Centroavante",
        "29",
        "FC Burnley"
    ]
  },
  "Inglaterra": {
    "grupo": "B",
    "Nome": "da Inglaterra",
    "Treinador": "Treinador",
    "flag": "assets/images/GrupoB/inglaterra/inglaterra.png",
    "0": [
        "22",
        "Meshaal Barsham",
        "Goleiro",
        "24",
        "Al-Sadd SC"
    ],
    "1": [
        "1",
        "Saad Al-Sheeb",
        "Goleiro",
        "32",
        "Al-Sadd SC"
    ],
    "2": [
        "21",
        "Yousef Hassan",
        "Goleiro",
        "25",
        "Al-Gharafa SC"
    ],
    "3": [
        "2",
        "Pedro Miguel",
        "Zagueiro",
        "31",
        "Al-Sadd SC"
    ],
    "4": [
        "5",
        "Tarek Salman",
        "Zagueiro",
        "31",
        "Al-Sadd SC"
    ],
    "5": [
        "15",
        "Bassam Al-Rawi",
        "Zagueiro",
        "24",
        "Al-Duhail SC"
    ],
    "6": [
        "16",
        "Boualem Khoukhi",
        "Zagueiro",
        "31",
        "Al-Sadd SC"
    ],
    "7": [
        "3",
        "Abdelkarim Hassan",
        "Lateral Esq.",
        "28",
        "Al-Sadd SC"
    ],
    "8": [
        "24",
        "Homam Ahmed",
        "Lateral Esq.",
        "22",
        "Al-Gharafa SC"
    ],
    "9": [
        "13",
        "Musab Khoder",
        "Lateral Dir.",
        "29",
        "Al-Sadd SC"
    ],
    "10": [
        "12",
        "Karim Boudiaf",
        "Volante",
        "31",
        "Al-Duhail SC"
    ],
    "11": [
        "23",
        "Assim Madibo",
        "Volante",
        "25",
        "Al-Duhail SC"
    ],
    "12": [
        "-",
        "Salem Al-Hajri",
        "Volante",
        "26",
        "Al-Sadd SC"
    ],
    "13": [
        "-",
        "Jassem Gaber Abdulsallam",
        "Volante",
        "20",
        "Al-Arabi SC"
    ],
    "14": [
        "-",
        "Abdulaziz Hatem",
        "Meia Central",
        "31",
        "Al-Rayyan SC"
    ],
    "15": [
        "-",
        "Ahmed Fathi",
        "Meia Central",
        "28",
        "Al-Arabi SC"
    ],
    "16": [
        "-",
        "Ahmad Doozandeh",
        "Meia Central",
        "26",
        "Qatar SC"
    ],
    "17": [
        "-",
        "Abdullah Marafee",
        "Meia Central",
        "30",
        "Al-Arabi SC"
    ],
    "18": [
        "4",
        "Mohammed Waad",
        "Meia Central",
        "22",
        "Al-Sadd SC"
    ],
    "19": [
        "22",
        "Abdullah Al-Ahrak",
        "Meia Ofensivo",
        "24",
        "Al-Sadd SC"
    ],
    "20": [
        "22",
        "Meshaal Barsham",
        "Goleiro",
        "24",
        "Al-Sadd SC"
    ],
    "21": [
        "22",
        "Meshaal Barsham",
        "Goleiro",
        "24",
        "Al-Sadd SC"
    ],
    "22": [
        "22",
        "Meshaal Barsham",
        "Goleiro",
        "24",
        "Al-Sadd SC"
    ],
    "23": [
        "22",
        "Meshaal Barsham",
        "Goleiro",
        "24",
        "Al-Sadd SC"
    ]
  },
  "Irã": {
    "grupo": "B",
    "Nome": "do Irã",
    "Treinador": "Treinador",
    "flag": "assets/images/GrupoB/irã/irã.png",
    "0": [
        "22",
        "Meshaal Barsham",
        "Goleiro",
        "24",
        "Al-Sadd SC"
    ],
    "1": [
        "1",
        "Saad Al-Sheeb",
        "Goleiro",
        "32",
        "Al-Sadd SC"
    ],
    "2": [
        "21",
        "Yousef Hassan",
        "Goleiro",
        "25",
        "Al-Gharafa SC"
    ],
    "3": [
        "2",
        "Pedro Miguel",
        "Zagueiro",
        "31",
        "Al-Sadd SC"
    ],
    "4": [
        "5",
        "Tarek Salman",
        "Zagueiro",
        "31",
        "Al-Sadd SC"
    ],
    "5": [
        "15",
        "Bassam Al-Rawi",
        "Zagueiro",
        "24",
        "Al-Duhail SC"
    ],
    "6": [
        "16",
        "Boualem Khoukhi",
        "Zagueiro",
        "31",
        "Al-Sadd SC"
    ],
    "7": [
        "3",
        "Abdelkarim Hassan",
        "Lateral Esq.",
        "28",
        "Al-Sadd SC"
    ],
    "8": [
        "24",
        "Homam Ahmed",
        "Lateral Esq.",
        "22",
        "Al-Gharafa SC"
    ],
    "9": [
        "13",
        "Musab Khoder",
        "Lateral Dir.",
        "29",
        "Al-Sadd SC"
    ],
    "10": [
        "12",
        "Karim Boudiaf",
        "Volante",
        "31",
        "Al-Duhail SC"
    ],
    "11": [
        "23",
        "Assim Madibo",
        "Volante",
        "25",
        "Al-Duhail SC"
    ],
    "12": [
        "-",
        "Salem Al-Hajri",
        "Volante",
        "26",
        "Al-Sadd SC"
    ],
    "13": [
        "-",
        "Jassem Gaber Abdulsallam",
        "Volante",
        "20",
        "Al-Arabi SC"
    ],
    "14": [
        "-",
        "Abdulaziz Hatem",
        "Meia Central",
        "31",
        "Al-Rayyan SC"
    ],
    "15": [
        "-",
        "Ahmed Fathi",
        "Meia Central",
        "28",
        "Al-Arabi SC"
    ],
    "16": [
        "-",
        "Ahmad Doozandeh",
        "Meia Central",
        "26",
        "Qatar SC"
    ],
    "17": [
        "-",
        "Abdullah Marafee",
        "Meia Central",
        "30",
        "Al-Arabi SC"
    ],
    "18": [
        "4",
        "Mohammed Waad",
        "Meia Central",
        "22",
        "Al-Sadd SC"
    ],
    "19": [
        "22",
        "Abdullah Al-Ahrak",
        "Meia Ofensivo",
        "24",
        "Al-Sadd SC"
    ],
    "20": [
        "22",
        "Meshaal Barsham",
        "Goleiro",
        "24",
        "Al-Sadd SC"
    ],
    "21": [
        "22",
        "Meshaal Barsham",
        "Goleiro",
        "24",
        "Al-Sadd SC"
    ],
    "22": [
        "22",
        "Meshaal Barsham",
        "Goleiro",
        "24",
        "Al-Sadd SC"
    ],
    "23": [
        "22",
        "Meshaal Barsham",
        "Goleiro",
        "24",
        "Al-Sadd SC"
    ]
  },
  "EUA": {
    "grupo": "B",
    "Nome": "dos EUA",
    "Treinador": "Treinador",
    "flag": "assets/images/GrupoB/eua/eua.png",
    "0": [
        "22",
        "Meshaal Barsham",
        "Goleiro",
        "24",
        "Al-Sadd SC"
    ],
    "1": [
        "1",
        "Saad Al-Sheeb",
        "Goleiro",
        "32",
        "Al-Sadd SC"
    ],
    "2": [
        "21",
        "Yousef Hassan",
        "Goleiro",
        "25",
        "Al-Gharafa SC"
    ],
    "3": [
        "2",
        "Pedro Miguel",
        "Zagueiro",
        "31",
        "Al-Sadd SC"
    ],
    "4": [
        "5",
        "Tarek Salman",
        "Zagueiro",
        "31",
        "Al-Sadd SC"
    ],
    "5": [
        "15",
        "Bassam Al-Rawi",
        "Zagueiro",
        "24",
        "Al-Duhail SC"
    ],
    "6": [
        "16",
        "Boualem Khoukhi",
        "Zagueiro",
        "31",
        "Al-Sadd SC"
    ],
    "7": [
        "3",
        "Abdelkarim Hassan",
        "Lateral Esq.",
        "28",
        "Al-Sadd SC"
    ],
    "8": [
        "24",
        "Homam Ahmed",
        "Lateral Esq.",
        "22",
        "Al-Gharafa SC"
    ],
    "9": [
        "13",
        "Musab Khoder",
        "Lateral Dir.",
        "29",
        "Al-Sadd SC"
    ],
    "10": [
        "12",
        "Karim Boudiaf",
        "Volante",
        "31",
        "Al-Duhail SC"
    ],
    "11": [
        "23",
        "Assim Madibo",
        "Volante",
        "25",
        "Al-Duhail SC"
    ],
    "12": [
        "-",
        "Salem Al-Hajri",
        "Volante",
        "26",
        "Al-Sadd SC"
    ],
    "13": [
        "-",
        "Jassem Gaber Abdulsallam",
        "Volante",
        "20",
        "Al-Arabi SC"
    ],
    "14": [
        "-",
        "Abdulaziz Hatem",
        "Meia Central",
        "31",
        "Al-Rayyan SC"
    ],
    "15": [
        "-",
        "Ahmed Fathi",
        "Meia Central",
        "28",
        "Al-Arabi SC"
    ],
    "16": [
        "-",
        "Ahmad Doozandeh",
        "Meia Central",
        "26",
        "Qatar SC"
    ],
    "17": [
        "-",
        "Abdullah Marafee",
        "Meia Central",
        "30",
        "Al-Arabi SC"
    ],
    "18": [
        "4",
        "Mohammed Waad",
        "Meia Central",
        "22",
        "Al-Sadd SC"
    ],
    "19": [
        "22",
        "Abdullah Al-Ahrak",
        "Meia Ofensivo",
        "24",
        "Al-Sadd SC"
    ],
    "20": [
        "22",
        "Meshaal Barsham",
        "Goleiro",
        "24",
        "Al-Sadd SC"
    ],
    "21": [
        "22",
        "Meshaal Barsham",
        "Goleiro",
        "24",
        "Al-Sadd SC"
    ],
    "22": [
        "22",
        "Meshaal Barsham",
        "Goleiro",
        "24",
        "Al-Sadd SC"
    ],
    "23": [
        "22",
        "Meshaal Barsham",
        "Goleiro",
        "24",
        "Al-Sadd SC"
    ]
  },
  "euro play-off": {
    "grupo": "B",
    "Nome": "do Euro Play-off",
    "Treinador": "Treinador",
    "flag": "assets/images/GrupoB/euro play-off/euro play-off.png",
    "0": [
        "22",
        "Meshaal Barsham",
        "Goleiro",
        "24",
        "Al-Sadd SC"
    ],
    "1": [
        "1",
        "Saad Al-Sheeb",
        "Goleiro",
        "32",
        "Al-Sadd SC"
    ],
    "2": [
        "21",
        "Yousef Hassan",
        "Goleiro",
        "25",
        "Al-Gharafa SC"
    ],
    "3": [
        "2",
        "Pedro Miguel",
        "Zagueiro",
        "31",
        "Al-Sadd SC"
    ],
    "4": [
        "5",
        "Tarek Salman",
        "Zagueiro",
        "31",
        "Al-Sadd SC"
    ],
    "5": [
        "15",
        "Bassam Al-Rawi",
        "Zagueiro",
        "24",
        "Al-Duhail SC"
    ],
    "6": [
        "16",
        "Boualem Khoukhi",
        "Zagueiro",
        "31",
        "Al-Sadd SC"
    ],
    "7": [
        "3",
        "Abdelkarim Hassan",
        "Lateral Esq.",
        "28",
        "Al-Sadd SC"
    ],
    "8": [
        "24",
        "Homam Ahmed",
        "Lateral Esq.",
        "22",
        "Al-Gharafa SC"
    ],
    "9": [
        "13",
        "Musab Khoder",
        "Lateral Dir.",
        "29",
        "Al-Sadd SC"
    ],
    "10": [
        "12",
        "Karim Boudiaf",
        "Volante",
        "31",
        "Al-Duhail SC"
    ],
    "11": [
        "23",
        "Assim Madibo",
        "Volante",
        "25",
        "Al-Duhail SC"
    ],
    "12": [
        "-",
        "Salem Al-Hajri",
        "Volante",
        "26",
        "Al-Sadd SC"
    ],
    "13": [
        "-",
        "Jassem Gaber Abdulsallam",
        "Volante",
        "20",
        "Al-Arabi SC"
    ],
    "14": [
        "-",
        "Abdulaziz Hatem",
        "Meia Central",
        "31",
        "Al-Rayyan SC"
    ],
    "15": [
        "-",
        "Ahmed Fathi",
        "Meia Central",
        "28",
        "Al-Arabi SC"
    ],
    "16": [
        "-",
        "Ahmad Doozandeh",
        "Meia Central",
        "26",
        "Qatar SC"
    ],
    "17": [
        "-",
        "Abdullah Marafee",
        "Meia Central",
        "30",
        "Al-Arabi SC"
    ],
    "18": [
        "4",
        "Mohammed Waad",
        "Meia Central",
        "22",
        "Al-Sadd SC"
    ],
    "19": [
        "22",
        "Abdullah Al-Ahrak",
        "Meia Ofensivo",
        "24",
        "Al-Sadd SC"
    ],
    "20": [
        "22",
        "Meshaal Barsham",
        "Goleiro",
        "24",
        "Al-Sadd SC"
    ],
    "21": [
        "22",
        "Meshaal Barsham",
        "Goleiro",
        "24",
        "Al-Sadd SC"
    ],
    "22": [
        "22",
        "Meshaal Barsham",
        "Goleiro",
        "24",
        "Al-Sadd SC"
    ],
    "23": [
        "22",
        "Meshaal Barsham",
        "Goleiro",
        "24",
        "Al-Sadd SC"
    ]
  },
  "Argentina": {
    "grupo": "C",
    "Nome": "da Argentina",
    "Treinador": "Treinador",
    "flag": "assets/images/GrupoC/argentina/argentina.png",
    "0": [
        "22",
        "Meshaal Barsham",
        "Goleiro",
        "24",
        "Al-Sadd SC"
    ],
    "1": [
        "1",
        "Saad Al-Sheeb",
        "Goleiro",
        "32",
        "Al-Sadd SC"
    ],
    "2": [
        "21",
        "Yousef Hassan",
        "Goleiro",
        "25",
        "Al-Gharafa SC"
    ],
    "3": [
        "2",
        "Pedro Miguel",
        "Zagueiro",
        "31",
        "Al-Sadd SC"
    ],
    "4": [
        "5",
        "Tarek Salman",
        "Zagueiro",
        "31",
        "Al-Sadd SC"
    ],
    "5": [
        "15",
        "Bassam Al-Rawi",
        "Zagueiro",
        "24",
        "Al-Duhail SC"
    ],
    "6": [
        "16",
        "Boualem Khoukhi",
        "Zagueiro",
        "31",
        "Al-Sadd SC"
    ],
    "7": [
        "3",
        "Abdelkarim Hassan",
        "Lateral Esq.",
        "28",
        "Al-Sadd SC"
    ],
    "8": [
        "24",
        "Homam Ahmed",
        "Lateral Esq.",
        "22",
        "Al-Gharafa SC"
    ],
    "9": [
        "13",
        "Musab Khoder",
        "Lateral Dir.",
        "29",
        "Al-Sadd SC"
    ],
    "10": [
        "12",
        "Karim Boudiaf",
        "Volante",
        "31",
        "Al-Duhail SC"
    ],
    "11": [
        "23",
        "Assim Madibo",
        "Volante",
        "25",
        "Al-Duhail SC"
    ],
    "12": [
        "-",
        "Salem Al-Hajri",
        "Volante",
        "26",
        "Al-Sadd SC"
    ],
    "13": [
        "-",
        "Jassem Gaber Abdulsallam",
        "Volante",
        "20",
        "Al-Arabi SC"
    ],
    "14": [
        "-",
        "Abdulaziz Hatem",
        "Meia Central",
        "31",
        "Al-Rayyan SC"
    ],
    "15": [
        "-",
        "Ahmed Fathi",
        "Meia Central",
        "28",
        "Al-Arabi SC"
    ],
    "16": [
        "-",
        "Ahmad Doozandeh",
        "Meia Central",
        "26",
        "Qatar SC"
    ],
    "17": [
        "-",
        "Abdullah Marafee",
        "Meia Central",
        "30",
        "Al-Arabi SC"
    ],
    "18": [
        "4",
        "Mohammed Waad",
        "Meia Central",
        "22",
        "Al-Sadd SC"
    ],
    "19": [
        "22",
        "Abdullah Al-Ahrak",
        "Meia Ofensivo",
        "24",
        "Al-Sadd SC"
    ],
    "20": [
        "22",
        "Meshaal Barsham",
        "Goleiro",
        "24",
        "Al-Sadd SC"
    ],
    "21": [
        "22",
        "Meshaal Barsham",
        "Goleiro",
        "24",
        "Al-Sadd SC"
    ],
    "22": [
        "22",
        "Meshaal Barsham",
        "Goleiro",
        "24",
        "Al-Sadd SC"
    ],
    "23": [
        "22",
        "Meshaal Barsham",
        "Goleiro",
        "24",
        "Al-Sadd SC"
    ]
  },
  "Arábia Saudita": {
    "grupo": "C",
    "Nome": "da Arábia Saudita ",
    "Treinador": "Treinador",
    "flag": "assets/images/GrupoC/arábia saudita/arábia saudita.png",
    "0": [
        "22",
        "Meshaal Barsham",
        "Goleiro",
        "24",
        "Al-Sadd SC"
    ],
    "1": [
        "1",
        "Saad Al-Sheeb",
        "Goleiro",
        "32",
        "Al-Sadd SC"
    ],
    "2": [
        "21",
        "Yousef Hassan",
        "Goleiro",
        "25",
        "Al-Gharafa SC"
    ],
    "3": [
        "2",
        "Pedro Miguel",
        "Zagueiro",
        "31",
        "Al-Sadd SC"
    ],
    "4": [
        "5",
        "Tarek Salman",
        "Zagueiro",
        "31",
        "Al-Sadd SC"
    ],
    "5": [
        "15",
        "Bassam Al-Rawi",
        "Zagueiro",
        "24",
        "Al-Duhail SC"
    ],
    "6": [
        "16",
        "Boualem Khoukhi",
        "Zagueiro",
        "31",
        "Al-Sadd SC"
    ],
    "7": [
        "3",
        "Abdelkarim Hassan",
        "Lateral Esq.",
        "28",
        "Al-Sadd SC"
    ],
    "8": [
        "24",
        "Homam Ahmed",
        "Lateral Esq.",
        "22",
        "Al-Gharafa SC"
    ],
    "9": [
        "13",
        "Musab Khoder",
        "Lateral Dir.",
        "29",
        "Al-Sadd SC"
    ],
    "10": [
        "12",
        "Karim Boudiaf",
        "Volante",
        "31",
        "Al-Duhail SC"
    ],
    "11": [
        "23",
        "Assim Madibo",
        "Volante",
        "25",
        "Al-Duhail SC"
    ],
    "12": [
        "-",
        "Salem Al-Hajri",
        "Volante",
        "26",
        "Al-Sadd SC"
    ],
    "13": [
        "-",
        "Jassem Gaber Abdulsallam",
        "Volante",
        "20",
        "Al-Arabi SC"
    ],
    "14": [
        "-",
        "Abdulaziz Hatem",
        "Meia Central",
        "31",
        "Al-Rayyan SC"
    ],
    "15": [
        "-",
        "Ahmed Fathi",
        "Meia Central",
        "28",
        "Al-Arabi SC"
    ],
    "16": [
        "-",
        "Ahmad Doozandeh",
        "Meia Central",
        "26",
        "Qatar SC"
    ],
    "17": [
        "-",
        "Abdullah Marafee",
        "Meia Central",
        "30",
        "Al-Arabi SC"
    ],
    "18": [
        "4",
        "Mohammed Waad",
        "Meia Central",
        "22",
        "Al-Sadd SC"
    ],
    "19": [
        "22",
        "Abdullah Al-Ahrak",
        "Meia Ofensivo",
        "24",
        "Al-Sadd SC"
    ],
    "20": [
        "22",
        "Meshaal Barsham",
        "Goleiro",
        "24",
        "Al-Sadd SC"
    ],
    "21": [
        "22",
        "Meshaal Barsham",
        "Goleiro",
        "24",
        "Al-Sadd SC"
    ],
    "22": [
        "22",
        "Meshaal Barsham",
        "Goleiro",
        "24",
        "Al-Sadd SC"
    ],
    "23": [
        "22",
        "Meshaal Barsham",
        "Goleiro",
        "24",
        "Al-Sadd SC"
    ]
  },
  "México": {
    "grupo": "C",
    "Nome": "do México",
    "Treinador": "Treinador",
    "flag": "assets/images/GrupoC/méxico/méxico.png",
    "0": [
        "22",
        "Meshaal Barsham",
        "Goleiro",
        "24",
        "Al-Sadd SC"
    ],
    "1": [
        "1",
        "Saad Al-Sheeb",
        "Goleiro",
        "32",
        "Al-Sadd SC"
    ],
    "2": [
        "21",
        "Yousef Hassan",
        "Goleiro",
        "25",
        "Al-Gharafa SC"
    ],
    "3": [
        "2",
        "Pedro Miguel",
        "Zagueiro",
        "31",
        "Al-Sadd SC"
    ],
    "4": [
        "5",
        "Tarek Salman",
        "Zagueiro",
        "31",
        "Al-Sadd SC"
    ],
    "5": [
        "15",
        "Bassam Al-Rawi",
        "Zagueiro",
        "24",
        "Al-Duhail SC"
    ],
    "6": [
        "16",
        "Boualem Khoukhi",
        "Zagueiro",
        "31",
        "Al-Sadd SC"
    ],
    "7": [
        "3",
        "Abdelkarim Hassan",
        "Lateral Esq.",
        "28",
        "Al-Sadd SC"
    ],
    "8": [
        "24",
        "Homam Ahmed",
        "Lateral Esq.",
        "22",
        "Al-Gharafa SC"
    ],
    "9": [
        "13",
        "Musab Khoder",
        "Lateral Dir.",
        "29",
        "Al-Sadd SC"
    ],
    "10": [
        "12",
        "Karim Boudiaf",
        "Volante",
        "31",
        "Al-Duhail SC"
    ],
    "11": [
        "23",
        "Assim Madibo",
        "Volante",
        "25",
        "Al-Duhail SC"
    ],
    "12": [
        "-",
        "Salem Al-Hajri",
        "Volante",
        "26",
        "Al-Sadd SC"
    ],
    "13": [
        "-",
        "Jassem Gaber Abdulsallam",
        "Volante",
        "20",
        "Al-Arabi SC"
    ],
    "14": [
        "-",
        "Abdulaziz Hatem",
        "Meia Central",
        "31",
        "Al-Rayyan SC"
    ],
    "15": [
        "-",
        "Ahmed Fathi",
        "Meia Central",
        "28",
        "Al-Arabi SC"
    ],
    "16": [
        "-",
        "Ahmad Doozandeh",
        "Meia Central",
        "26",
        "Qatar SC"
    ],
    "17": [
        "-",
        "Abdullah Marafee",
        "Meia Central",
        "30",
        "Al-Arabi SC"
    ],
    "18": [
        "4",
        "Mohammed Waad",
        "Meia Central",
        "22",
        "Al-Sadd SC"
    ],
    "19": [
        "22",
        "Abdullah Al-Ahrak",
        "Meia Ofensivo",
        "24",
        "Al-Sadd SC"
    ],
    "20": [
        "22",
        "Meshaal Barsham",
        "Goleiro",
        "24",
        "Al-Sadd SC"
    ],
    "21": [
        "22",
        "Meshaal Barsham",
        "Goleiro",
        "24",
        "Al-Sadd SC"
    ],
    "22": [
        "22",
        "Meshaal Barsham",
        "Goleiro",
        "24",
        "Al-Sadd SC"
    ],
    "23": [
        "22",
        "Meshaal Barsham",
        "Goleiro",
        "24",
        "Al-Sadd SC"
    ]
  },
  "Polônia": {
    "grupo": "C",
    "Nome": "da Polônia",
    "Treinador": "Treinador",
    "flag": "assets/images/GrupoC/polônia/polônia.png",
    "0": [
        "22",
        "Meshaal Barsham",
        "Goleiro",
        "24",
        "Al-Sadd SC"
    ],
    "1": [
        "1",
        "Saad Al-Sheeb",
        "Goleiro",
        "32",
        "Al-Sadd SC"
    ],
    "2": [
        "21",
        "Yousef Hassan",
        "Goleiro",
        "25",
        "Al-Gharafa SC"
    ],
    "3": [
        "2",
        "Pedro Miguel",
        "Zagueiro",
        "31",
        "Al-Sadd SC"
    ],
    "4": [
        "5",
        "Tarek Salman",
        "Zagueiro",
        "31",
        "Al-Sadd SC"
    ],
    "5": [
        "15",
        "Bassam Al-Rawi",
        "Zagueiro",
        "24",
        "Al-Duhail SC"
    ],
    "6": [
        "16",
        "Boualem Khoukhi",
        "Zagueiro",
        "31",
        "Al-Sadd SC"
    ],
    "7": [
        "3",
        "Abdelkarim Hassan",
        "Lateral Esq.",
        "28",
        "Al-Sadd SC"
    ],
    "8": [
        "24",
        "Homam Ahmed",
        "Lateral Esq.",
        "22",
        "Al-Gharafa SC"
    ],
    "9": [
        "13",
        "Musab Khoder",
        "Lateral Dir.",
        "29",
        "Al-Sadd SC"
    ],
    "10": [
        "12",
        "Karim Boudiaf",
        "Volante",
        "31",
        "Al-Duhail SC"
    ],
    "11": [
        "23",
        "Assim Madibo",
        "Volante",
        "25",
        "Al-Duhail SC"
    ],
    "12": [
        "-",
        "Salem Al-Hajri",
        "Volante",
        "26",
        "Al-Sadd SC"
    ],
    "13": [
        "-",
        "Jassem Gaber Abdulsallam",
        "Volante",
        "20",
        "Al-Arabi SC"
    ],
    "14": [
        "-",
        "Abdulaziz Hatem",
        "Meia Central",
        "31",
        "Al-Rayyan SC"
    ],
    "15": [
        "-",
        "Ahmed Fathi",
        "Meia Central",
        "28",
        "Al-Arabi SC"
    ],
    "16": [
        "-",
        "Ahmad Doozandeh",
        "Meia Central",
        "26",
        "Qatar SC"
    ],
    "17": [
        "-",
        "Abdullah Marafee",
        "Meia Central",
        "30",
        "Al-Arabi SC"
    ],
    "18": [
        "4",
        "Mohammed Waad",
        "Meia Central",
        "22",
        "Al-Sadd SC"
    ],
    "19": [
        "22",
        "Abdullah Al-Ahrak",
        "Meia Ofensivo",
        "24",
        "Al-Sadd SC"
    ],
    "20": [
        "22",
        "Meshaal Barsham",
        "Goleiro",
        "24",
        "Al-Sadd SC"
    ],
    "21": [
        "22",
        "Meshaal Barsham",
        "Goleiro",
        "24",
        "Al-Sadd SC"
    ],
    "22": [
        "22",
        "Meshaal Barsham",
        "Goleiro",
        "24",
        "Al-Sadd SC"
    ],
    "23": [
        "22",
        "Meshaal Barsham",
        "Goleiro",
        "24",
        "Al-Sadd SC"
    ]
  },
  "França": {
    "grupo": "D",
    "Nome": "da França",
    "Treinador": "Treinador",
    "flag": "assets/images/GrupoD/frança/frança.png",
    "0": [
        "22",
        "Meshaal Barsham",
        "Goleiro",
        "24",
        "Al-Sadd SC"
    ],
    "1": [
        "1",
        "Saad Al-Sheeb",
        "Goleiro",
        "32",
        "Al-Sadd SC"
    ],
    "2": [
        "21",
        "Yousef Hassan",
        "Goleiro",
        "25",
        "Al-Gharafa SC"
    ],
    "3": [
        "2",
        "Pedro Miguel",
        "Zagueiro",
        "31",
        "Al-Sadd SC"
    ],
    "4": [
        "5",
        "Tarek Salman",
        "Zagueiro",
        "31",
        "Al-Sadd SC"
    ],
    "5": [
        "15",
        "Bassam Al-Rawi",
        "Zagueiro",
        "24",
        "Al-Duhail SC"
    ],
    "6": [
        "16",
        "Boualem Khoukhi",
        "Zagueiro",
        "31",
        "Al-Sadd SC"
    ],
    "7": [
        "3",
        "Abdelkarim Hassan",
        "Lateral Esq.",
        "28",
        "Al-Sadd SC"
    ],
    "8": [
        "24",
        "Homam Ahmed",
        "Lateral Esq.",
        "22",
        "Al-Gharafa SC"
    ],
    "9": [
        "13",
        "Musab Khoder",
        "Lateral Dir.",
        "29",
        "Al-Sadd SC"
    ],
    "10": [
        "12",
        "Karim Boudiaf",
        "Volante",
        "31",
        "Al-Duhail SC"
    ],
    "11": [
        "23",
        "Assim Madibo",
        "Volante",
        "25",
        "Al-Duhail SC"
    ],
    "12": [
        "-",
        "Salem Al-Hajri",
        "Volante",
        "26",
        "Al-Sadd SC"
    ],
    "13": [
        "-",
        "Jassem Gaber Abdulsallam",
        "Volante",
        "20",
        "Al-Arabi SC"
    ],
    "14": [
        "-",
        "Abdulaziz Hatem",
        "Meia Central",
        "31",
        "Al-Rayyan SC"
    ],
    "15": [
        "-",
        "Ahmed Fathi",
        "Meia Central",
        "28",
        "Al-Arabi SC"
    ],
    "16": [
        "-",
        "Ahmad Doozandeh",
        "Meia Central",
        "26",
        "Qatar SC"
    ],
    "17": [
        "-",
        "Abdullah Marafee",
        "Meia Central",
        "30",
        "Al-Arabi SC"
    ],
    "18": [
        "4",
        "Mohammed Waad",
        "Meia Central",
        "22",
        "Al-Sadd SC"
    ],
    "19": [
        "22",
        "Abdullah Al-Ahrak",
        "Meia Ofensivo",
        "24",
        "Al-Sadd SC"
    ],
    "20": [
        "22",
        "Meshaal Barsham",
        "Goleiro",
        "24",
        "Al-Sadd SC"
    ],
    "21": [
        "22",
        "Meshaal Barsham",
        "Goleiro",
        "24",
        "Al-Sadd SC"
    ],
    "22": [
        "22",
        "Meshaal Barsham",
        "Goleiro",
        "24",
        "Al-Sadd SC"
    ],
    "23": [
        "22",
        "Meshaal Barsham",
        "Goleiro",
        "24",
        "Al-Sadd SC"
    ]
  },
  "ic play-off 1": {
    "grupo": "D",
    "Nome": "da IC Play-off 1",
    "Treinador": "Treinador",
    "flag": "assets/images/GrupoD/ic play-off 1/ic play-off 1.png",
    "0": [
        "22",
        "Meshaal Barsham",
        "Goleiro",
        "24",
        "Al-Sadd SC"
    ],
    "1": [
        "1",
        "Saad Al-Sheeb",
        "Goleiro",
        "32",
        "Al-Sadd SC"
    ],
    "2": [
        "21",
        "Yousef Hassan",
        "Goleiro",
        "25",
        "Al-Gharafa SC"
    ],
    "3": [
        "2",
        "Pedro Miguel",
        "Zagueiro",
        "31",
        "Al-Sadd SC"
    ],
    "4": [
        "5",
        "Tarek Salman",
        "Zagueiro",
        "31",
        "Al-Sadd SC"
    ],
    "5": [
        "15",
        "Bassam Al-Rawi",
        "Zagueiro",
        "24",
        "Al-Duhail SC"
    ],
    "6": [
        "16",
        "Boualem Khoukhi",
        "Zagueiro",
        "31",
        "Al-Sadd SC"
    ],
    "7": [
        "3",
        "Abdelkarim Hassan",
        "Lateral Esq.",
        "28",
        "Al-Sadd SC"
    ],
    "8": [
        "24",
        "Homam Ahmed",
        "Lateral Esq.",
        "22",
        "Al-Gharafa SC"
    ],
    "9": [
        "13",
        "Musab Khoder",
        "Lateral Dir.",
        "29",
        "Al-Sadd SC"
    ],
    "10": [
        "12",
        "Karim Boudiaf",
        "Volante",
        "31",
        "Al-Duhail SC"
    ],
    "11": [
        "23",
        "Assim Madibo",
        "Volante",
        "25",
        "Al-Duhail SC"
    ],
    "12": [
        "-",
        "Salem Al-Hajri",
        "Volante",
        "26",
        "Al-Sadd SC"
    ],
    "13": [
        "-",
        "Jassem Gaber Abdulsallam",
        "Volante",
        "20",
        "Al-Arabi SC"
    ],
    "14": [
        "-",
        "Abdulaziz Hatem",
        "Meia Central",
        "31",
        "Al-Rayyan SC"
    ],
    "15": [
        "-",
        "Ahmed Fathi",
        "Meia Central",
        "28",
        "Al-Arabi SC"
    ],
    "16": [
        "-",
        "Ahmad Doozandeh",
        "Meia Central",
        "26",
        "Qatar SC"
    ],
    "17": [
        "-",
        "Abdullah Marafee",
        "Meia Central",
        "30",
        "Al-Arabi SC"
    ],
    "18": [
        "4",
        "Mohammed Waad",
        "Meia Central",
        "22",
        "Al-Sadd SC"
    ],
    "19": [
        "22",
        "Abdullah Al-Ahrak",
        "Meia Ofensivo",
        "24",
        "Al-Sadd SC"
    ],
    "20": [
        "22",
        "Meshaal Barsham",
        "Goleiro",
        "24",
        "Al-Sadd SC"
    ],
    "21": [
        "22",
        "Meshaal Barsham",
        "Goleiro",
        "24",
        "Al-Sadd SC"
    ],
    "22": [
        "22",
        "Meshaal Barsham",
        "Goleiro",
        "24",
        "Al-Sadd SC"
    ],
    "23": [
        "22",
        "Meshaal Barsham",
        "Goleiro",
        "24",
        "Al-Sadd SC"
    ]
  },
  "Dinamarca": {
    "grupo": "D",
    "Nome": "da Dinamarca",
    "Treinador": "Treinador",
    "flag": "assets/images/GrupoD/dinamarca/dinamarca.png",
    "0": [
        "22",
        "Meshaal Barsham",
        "Goleiro",
        "24",
        "Al-Sadd SC"
    ],
    "1": [
        "1",
        "Saad Al-Sheeb",
        "Goleiro",
        "32",
        "Al-Sadd SC"
    ],
    "2": [
        "21",
        "Yousef Hassan",
        "Goleiro",
        "25",
        "Al-Gharafa SC"
    ],
    "3": [
        "2",
        "Pedro Miguel",
        "Zagueiro",
        "31",
        "Al-Sadd SC"
    ],
    "4": [
        "5",
        "Tarek Salman",
        "Zagueiro",
        "31",
        "Al-Sadd SC"
    ],
    "5": [
        "15",
        "Bassam Al-Rawi",
        "Zagueiro",
        "24",
        "Al-Duhail SC"
    ],
    "6": [
        "16",
        "Boualem Khoukhi",
        "Zagueiro",
        "31",
        "Al-Sadd SC"
    ],
    "7": [
        "3",
        "Abdelkarim Hassan",
        "Lateral Esq.",
        "28",
        "Al-Sadd SC"
    ],
    "8": [
        "24",
        "Homam Ahmed",
        "Lateral Esq.",
        "22",
        "Al-Gharafa SC"
    ],
    "9": [
        "13",
        "Musab Khoder",
        "Lateral Dir.",
        "29",
        "Al-Sadd SC"
    ],
    "10": [
        "12",
        "Karim Boudiaf",
        "Volante",
        "31",
        "Al-Duhail SC"
    ],
    "11": [
        "23",
        "Assim Madibo",
        "Volante",
        "25",
        "Al-Duhail SC"
    ],
    "12": [
        "-",
        "Salem Al-Hajri",
        "Volante",
        "26",
        "Al-Sadd SC"
    ],
    "13": [
        "-",
        "Jassem Gaber Abdulsallam",
        "Volante",
        "20",
        "Al-Arabi SC"
    ],
    "14": [
        "-",
        "Abdulaziz Hatem",
        "Meia Central",
        "31",
        "Al-Rayyan SC"
    ],
    "15": [
        "-",
        "Ahmed Fathi",
        "Meia Central",
        "28",
        "Al-Arabi SC"
    ],
    "16": [
        "-",
        "Ahmad Doozandeh",
        "Meia Central",
        "26",
        "Qatar SC"
    ],
    "17": [
        "-",
        "Abdullah Marafee",
        "Meia Central",
        "30",
        "Al-Arabi SC"
    ],
    "18": [
        "4",
        "Mohammed Waad",
        "Meia Central",
        "22",
        "Al-Sadd SC"
    ],
    "19": [
        "22",
        "Abdullah Al-Ahrak",
        "Meia Ofensivo",
        "24",
        "Al-Sadd SC"
    ],
    "20": [
        "22",
        "Meshaal Barsham",
        "Goleiro",
        "24",
        "Al-Sadd SC"
    ],
    "21": [
        "22",
        "Meshaal Barsham",
        "Goleiro",
        "24",
        "Al-Sadd SC"
    ],
    "22": [
        "22",
        "Meshaal Barsham",
        "Goleiro",
        "24",
        "Al-Sadd SC"
    ],
    "23": [
        "22",
        "Meshaal Barsham",
        "Goleiro",
        "24",
        "Al-Sadd SC"
    ]
  },
  "Tunísia": {
    "grupo": "D",
    "Nome": "da Tunísia",
    "Treinador": "Treinador",
    "flag": "assets/images/GrupoD/tunísia/tunísia.png",
    "0": [
        "22",
        "Meshaal Barsham",
        "Goleiro",
        "24",
        "Al-Sadd SC"
    ],
    "1": [
        "1",
        "Saad Al-Sheeb",
        "Goleiro",
        "32",
        "Al-Sadd SC"
    ],
    "2": [
        "21",
        "Yousef Hassan",
        "Goleiro",
        "25",
        "Al-Gharafa SC"
    ],
    "3": [
        "2",
        "Pedro Miguel",
        "Zagueiro",
        "31",
        "Al-Sadd SC"
    ],
    "4": [
        "5",
        "Tarek Salman",
        "Zagueiro",
        "31",
        "Al-Sadd SC"
    ],
    "5": [
        "15",
        "Bassam Al-Rawi",
        "Zagueiro",
        "24",
        "Al-Duhail SC"
    ],
    "6": [
        "16",
        "Boualem Khoukhi",
        "Zagueiro",
        "31",
        "Al-Sadd SC"
    ],
    "7": [
        "3",
        "Abdelkarim Hassan",
        "Lateral Esq.",
        "28",
        "Al-Sadd SC"
    ],
    "8": [
        "24",
        "Homam Ahmed",
        "Lateral Esq.",
        "22",
        "Al-Gharafa SC"
    ],
    "9": [
        "13",
        "Musab Khoder",
        "Lateral Dir.",
        "29",
        "Al-Sadd SC"
    ],
    "10": [
        "12",
        "Karim Boudiaf",
        "Volante",
        "31",
        "Al-Duhail SC"
    ],
    "11": [
        "23",
        "Assim Madibo",
        "Volante",
        "25",
        "Al-Duhail SC"
    ],
    "12": [
        "-",
        "Salem Al-Hajri",
        "Volante",
        "26",
        "Al-Sadd SC"
    ],
    "13": [
        "-",
        "Jassem Gaber Abdulsallam",
        "Volante",
        "20",
        "Al-Arabi SC"
    ],
    "14": [
        "-",
        "Abdulaziz Hatem",
        "Meia Central",
        "31",
        "Al-Rayyan SC"
    ],
    "15": [
        "-",
        "Ahmed Fathi",
        "Meia Central",
        "28",
        "Al-Arabi SC"
    ],
    "16": [
        "-",
        "Ahmad Doozandeh",
        "Meia Central",
        "26",
        "Qatar SC"
    ],
    "17": [
        "-",
        "Abdullah Marafee",
        "Meia Central",
        "30",
        "Al-Arabi SC"
    ],
    "18": [
        "4",
        "Mohammed Waad",
        "Meia Central",
        "22",
        "Al-Sadd SC"
    ],
    "19": [
        "22",
        "Abdullah Al-Ahrak",
        "Meia Ofensivo",
        "24",
        "Al-Sadd SC"
    ],
    "20": [
        "22",
        "Meshaal Barsham",
        "Goleiro",
        "24",
        "Al-Sadd SC"
    ],
    "21": [
        "22",
        "Meshaal Barsham",
        "Goleiro",
        "24",
        "Al-Sadd SC"
    ],
    "22": [
        "22",
        "Meshaal Barsham",
        "Goleiro",
        "24",
        "Al-Sadd SC"
    ],
    "23": [
        "22",
        "Meshaal Barsham",
        "Goleiro",
        "24",
        "Al-Sadd SC"
    ]
  },
  "Espanha": {
    "grupo": "E",
    "Nome": "da Espanha",
    "Treinador": "Treinador",
    "flag": "assets/images/GrupoE/espanha/espanha.png",
    "0": [
        "22",
        "Meshaal Barsham",
        "Goleiro",
        "24",
        "Al-Sadd SC"
    ],
    "1": [
        "1",
        "Saad Al-Sheeb",
        "Goleiro",
        "32",
        "Al-Sadd SC"
    ],
    "2": [
        "21",
        "Yousef Hassan",
        "Goleiro",
        "25",
        "Al-Gharafa SC"
    ],
    "3": [
        "2",
        "Pedro Miguel",
        "Zagueiro",
        "31",
        "Al-Sadd SC"
    ],
    "4": [
        "5",
        "Tarek Salman",
        "Zagueiro",
        "31",
        "Al-Sadd SC"
    ],
    "5": [
        "15",
        "Bassam Al-Rawi",
        "Zagueiro",
        "24",
        "Al-Duhail SC"
    ],
    "6": [
        "16",
        "Boualem Khoukhi",
        "Zagueiro",
        "31",
        "Al-Sadd SC"
    ],
    "7": [
        "3",
        "Abdelkarim Hassan",
        "Lateral Esq.",
        "28",
        "Al-Sadd SC"
    ],
    "8": [
        "24",
        "Homam Ahmed",
        "Lateral Esq.",
        "22",
        "Al-Gharafa SC"
    ],
    "9": [
        "13",
        "Musab Khoder",
        "Lateral Dir.",
        "29",
        "Al-Sadd SC"
    ],
    "10": [
        "12",
        "Karim Boudiaf",
        "Volante",
        "31",
        "Al-Duhail SC"
    ],
    "11": [
        "23",
        "Assim Madibo",
        "Volante",
        "25",
        "Al-Duhail SC"
    ],
    "12": [
        "-",
        "Salem Al-Hajri",
        "Volante",
        "26",
        "Al-Sadd SC"
    ],
    "13": [
        "-",
        "Jassem Gaber Abdulsallam",
        "Volante",
        "20",
        "Al-Arabi SC"
    ],
    "14": [
        "-",
        "Abdulaziz Hatem",
        "Meia Central",
        "31",
        "Al-Rayyan SC"
    ],
    "15": [
        "-",
        "Ahmed Fathi",
        "Meia Central",
        "28",
        "Al-Arabi SC"
    ],
    "16": [
        "-",
        "Ahmad Doozandeh",
        "Meia Central",
        "26",
        "Qatar SC"
    ],
    "17": [
        "-",
        "Abdullah Marafee",
        "Meia Central",
        "30",
        "Al-Arabi SC"
    ],
    "18": [
        "4",
        "Mohammed Waad",
        "Meia Central",
        "22",
        "Al-Sadd SC"
    ],
    "19": [
        "22",
        "Abdullah Al-Ahrak",
        "Meia Ofensivo",
        "24",
        "Al-Sadd SC"
    ],
    "20": [
        "22",
        "Meshaal Barsham",
        "Goleiro",
        "24",
        "Al-Sadd SC"
    ],
    "21": [
        "22",
        "Meshaal Barsham",
        "Goleiro",
        "24",
        "Al-Sadd SC"
    ],
    "22": [
        "22",
        "Meshaal Barsham",
        "Goleiro",
        "24",
        "Al-Sadd SC"
    ],
    "23": [
        "22",
        "Meshaal Barsham",
        "Goleiro",
        "24",
        "Al-Sadd SC"
    ]
  },
  "ic play-off 2": {
    "grupo": "E",
    "Nome": "da IC Play-off 2",
    "Treinador": "Treinador",
    "flag": "assets/images/GrupoE/ic play-off 2/ic play-off 2.png",
    "0": [
        "22",
        "Meshaal Barsham",
        "Goleiro",
        "24",
        "Al-Sadd SC"
    ],
    "1": [
        "1",
        "Saad Al-Sheeb",
        "Goleiro",
        "32",
        "Al-Sadd SC"
    ],
    "2": [
        "21",
        "Yousef Hassan",
        "Goleiro",
        "25",
        "Al-Gharafa SC"
    ],
    "3": [
        "2",
        "Pedro Miguel",
        "Zagueiro",
        "31",
        "Al-Sadd SC"
    ],
    "4": [
        "5",
        "Tarek Salman",
        "Zagueiro",
        "31",
        "Al-Sadd SC"
    ],
    "5": [
        "15",
        "Bassam Al-Rawi",
        "Zagueiro",
        "24",
        "Al-Duhail SC"
    ],
    "6": [
        "16",
        "Boualem Khoukhi",
        "Zagueiro",
        "31",
        "Al-Sadd SC"
    ],
    "7": [
        "3",
        "Abdelkarim Hassan",
        "Lateral Esq.",
        "28",
        "Al-Sadd SC"
    ],
    "8": [
        "24",
        "Homam Ahmed",
        "Lateral Esq.",
        "22",
        "Al-Gharafa SC"
    ],
    "9": [
        "13",
        "Musab Khoder",
        "Lateral Dir.",
        "29",
        "Al-Sadd SC"
    ],
    "10": [
        "12",
        "Karim Boudiaf",
        "Volante",
        "31",
        "Al-Duhail SC"
    ],
    "11": [
        "23",
        "Assim Madibo",
        "Volante",
        "25",
        "Al-Duhail SC"
    ],
    "12": [
        "-",
        "Salem Al-Hajri",
        "Volante",
        "26",
        "Al-Sadd SC"
    ],
    "13": [
        "-",
        "Jassem Gaber Abdulsallam",
        "Volante",
        "20",
        "Al-Arabi SC"
    ],
    "14": [
        "-",
        "Abdulaziz Hatem",
        "Meia Central",
        "31",
        "Al-Rayyan SC"
    ],
    "15": [
        "-",
        "Ahmed Fathi",
        "Meia Central",
        "28",
        "Al-Arabi SC"
    ],
    "16": [
        "-",
        "Ahmad Doozandeh",
        "Meia Central",
        "26",
        "Qatar SC"
    ],
    "17": [
        "-",
        "Abdullah Marafee",
        "Meia Central",
        "30",
        "Al-Arabi SC"
    ],
    "18": [
        "4",
        "Mohammed Waad",
        "Meia Central",
        "22",
        "Al-Sadd SC"
    ],
    "19": [
        "22",
        "Abdullah Al-Ahrak",
        "Meia Ofensivo",
        "24",
        "Al-Sadd SC"
    ],
    "20": [
        "22",
        "Meshaal Barsham",
        "Goleiro",
        "24",
        "Al-Sadd SC"
    ],
    "21": [
        "22",
        "Meshaal Barsham",
        "Goleiro",
        "24",
        "Al-Sadd SC"
    ],
    "22": [
        "22",
        "Meshaal Barsham",
        "Goleiro",
        "24",
        "Al-Sadd SC"
    ],
    "23": [
        "22",
        "Meshaal Barsham",
        "Goleiro",
        "24",
        "Al-Sadd SC"
    ]
  },
  "Alemanha": {
    "grupo": "E",
    "Nome": "da Alemanha",
    "Treinador": "Treinador",
    "flag": "assets/images/GrupoE/alemanha/alemanha.png",
    "0": [
        "22",
        "Meshaal Barsham",
        "Goleiro",
        "24",
        "Al-Sadd SC"
    ],
    "1": [
        "1",
        "Saad Al-Sheeb",
        "Goleiro",
        "32",
        "Al-Sadd SC"
    ],
    "2": [
        "21",
        "Yousef Hassan",
        "Goleiro",
        "25",
        "Al-Gharafa SC"
    ],
    "3": [
        "2",
        "Pedro Miguel",
        "Zagueiro",
        "31",
        "Al-Sadd SC"
    ],
    "4": [
        "5",
        "Tarek Salman",
        "Zagueiro",
        "31",
        "Al-Sadd SC"
    ],
    "5": [
        "15",
        "Bassam Al-Rawi",
        "Zagueiro",
        "24",
        "Al-Duhail SC"
    ],
    "6": [
        "16",
        "Boualem Khoukhi",
        "Zagueiro",
        "31",
        "Al-Sadd SC"
    ],
    "7": [
        "3",
        "Abdelkarim Hassan",
        "Lateral Esq.",
        "28",
        "Al-Sadd SC"
    ],
    "8": [
        "24",
        "Homam Ahmed",
        "Lateral Esq.",
        "22",
        "Al-Gharafa SC"
    ],
    "9": [
        "13",
        "Musab Khoder",
        "Lateral Dir.",
        "29",
        "Al-Sadd SC"
    ],
    "10": [
        "12",
        "Karim Boudiaf",
        "Volante",
        "31",
        "Al-Duhail SC"
    ],
    "11": [
        "23",
        "Assim Madibo",
        "Volante",
        "25",
        "Al-Duhail SC"
    ],
    "12": [
        "-",
        "Salem Al-Hajri",
        "Volante",
        "26",
        "Al-Sadd SC"
    ],
    "13": [
        "-",
        "Jassem Gaber Abdulsallam",
        "Volante",
        "20",
        "Al-Arabi SC"
    ],
    "14": [
        "-",
        "Abdulaziz Hatem",
        "Meia Central",
        "31",
        "Al-Rayyan SC"
    ],
    "15": [
        "-",
        "Ahmed Fathi",
        "Meia Central",
        "28",
        "Al-Arabi SC"
    ],
    "16": [
        "-",
        "Ahmad Doozandeh",
        "Meia Central",
        "26",
        "Qatar SC"
    ],
    "17": [
        "-",
        "Abdullah Marafee",
        "Meia Central",
        "30",
        "Al-Arabi SC"
    ],
    "18": [
        "4",
        "Mohammed Waad",
        "Meia Central",
        "22",
        "Al-Sadd SC"
    ],
    "19": [
        "22",
        "Abdullah Al-Ahrak",
        "Meia Ofensivo",
        "24",
        "Al-Sadd SC"
    ],
    "20": [
        "22",
        "Meshaal Barsham",
        "Goleiro",
        "24",
        "Al-Sadd SC"
    ],
    "21": [
        "22",
        "Meshaal Barsham",
        "Goleiro",
        "24",
        "Al-Sadd SC"
    ],
    "22": [
        "22",
        "Meshaal Barsham",
        "Goleiro",
        "24",
        "Al-Sadd SC"
    ],
    "23": [
        "22",
        "Meshaal Barsham",
        "Goleiro",
        "24",
        "Al-Sadd SC"
    ]
  },
  "Japão": {
    "grupo": "E",
    "Nome": "do Japão",
    "Treinador": "Treinador",
    "flag": "assets/images/GrupoE/japão/japão.png",
    "0": [
        "22",
        "Meshaal Barsham",
        "Goleiro",
        "24",
        "Al-Sadd SC"
    ],
    "1": [
        "1",
        "Saad Al-Sheeb",
        "Goleiro",
        "32",
        "Al-Sadd SC"
    ],
    "2": [
        "21",
        "Yousef Hassan",
        "Goleiro",
        "25",
        "Al-Gharafa SC"
    ],
    "3": [
        "2",
        "Pedro Miguel",
        "Zagueiro",
        "31",
        "Al-Sadd SC"
    ],
    "4": [
        "5",
        "Tarek Salman",
        "Zagueiro",
        "31",
        "Al-Sadd SC"
    ],
    "5": [
        "15",
        "Bassam Al-Rawi",
        "Zagueiro",
        "24",
        "Al-Duhail SC"
    ],
    "6": [
        "16",
        "Boualem Khoukhi",
        "Zagueiro",
        "31",
        "Al-Sadd SC"
    ],
    "7": [
        "3",
        "Abdelkarim Hassan",
        "Lateral Esq.",
        "28",
        "Al-Sadd SC"
    ],
    "8": [
        "24",
        "Homam Ahmed",
        "Lateral Esq.",
        "22",
        "Al-Gharafa SC"
    ],
    "9": [
        "13",
        "Musab Khoder",
        "Lateral Dir.",
        "29",
        "Al-Sadd SC"
    ],
    "10": [
        "12",
        "Karim Boudiaf",
        "Volante",
        "31",
        "Al-Duhail SC"
    ],
    "11": [
        "23",
        "Assim Madibo",
        "Volante",
        "25",
        "Al-Duhail SC"
    ],
    "12": [
        "-",
        "Salem Al-Hajri",
        "Volante",
        "26",
        "Al-Sadd SC"
    ],
    "13": [
        "-",
        "Jassem Gaber Abdulsallam",
        "Volante",
        "20",
        "Al-Arabi SC"
    ],
    "14": [
        "-",
        "Abdulaziz Hatem",
        "Meia Central",
        "31",
        "Al-Rayyan SC"
    ],
    "15": [
        "-",
        "Ahmed Fathi",
        "Meia Central",
        "28",
        "Al-Arabi SC"
    ],
    "16": [
        "-",
        "Ahmad Doozandeh",
        "Meia Central",
        "26",
        "Qatar SC"
    ],
    "17": [
        "-",
        "Abdullah Marafee",
        "Meia Central",
        "30",
        "Al-Arabi SC"
    ],
    "18": [
        "4",
        "Mohammed Waad",
        "Meia Central",
        "22",
        "Al-Sadd SC"
    ],
    "19": [
        "22",
        "Abdullah Al-Ahrak",
        "Meia Ofensivo",
        "24",
        "Al-Sadd SC"
    ],
    "20": [
        "22",
        "Meshaal Barsham",
        "Goleiro",
        "24",
        "Al-Sadd SC"
    ],
    "21": [
        "22",
        "Meshaal Barsham",
        "Goleiro",
        "24",
        "Al-Sadd SC"
    ],
    "22": [
        "22",
        "Meshaal Barsham",
        "Goleiro",
        "24",
        "Al-Sadd SC"
    ],
    "23": [
        "22",
        "Meshaal Barsham",
        "Goleiro",
        "24",
        "Al-Sadd SC"
    ]
  },
  "Bélgica": {
    "grupo": "F",
    "Nome": "da Bélgica",
    "Treinador": "Treinador",
    "flag": "assets/images/GrupoF/bélgica/bélgica.png",
    "0": [
        "22",
        "Meshaal Barsham",
        "Goleiro",
        "24",
        "Al-Sadd SC"
    ],
    "1": [
        "1",
        "Saad Al-Sheeb",
        "Goleiro",
        "32",
        "Al-Sadd SC"
    ],
    "2": [
        "21",
        "Yousef Hassan",
        "Goleiro",
        "25",
        "Al-Gharafa SC"
    ],
    "3": [
        "2",
        "Pedro Miguel",
        "Zagueiro",
        "31",
        "Al-Sadd SC"
    ],
    "4": [
        "5",
        "Tarek Salman",
        "Zagueiro",
        "31",
        "Al-Sadd SC"
    ],
    "5": [
        "15",
        "Bassam Al-Rawi",
        "Zagueiro",
        "24",
        "Al-Duhail SC"
    ],
    "6": [
        "16",
        "Boualem Khoukhi",
        "Zagueiro",
        "31",
        "Al-Sadd SC"
    ],
    "7": [
        "3",
        "Abdelkarim Hassan",
        "Lateral Esq.",
        "28",
        "Al-Sadd SC"
    ],
    "8": [
        "24",
        "Homam Ahmed",
        "Lateral Esq.",
        "22",
        "Al-Gharafa SC"
    ],
    "9": [
        "13",
        "Musab Khoder",
        "Lateral Dir.",
        "29",
        "Al-Sadd SC"
    ],
    "10": [
        "12",
        "Karim Boudiaf",
        "Volante",
        "31",
        "Al-Duhail SC"
    ],
    "11": [
        "23",
        "Assim Madibo",
        "Volante",
        "25",
        "Al-Duhail SC"
    ],
    "12": [
        "-",
        "Salem Al-Hajri",
        "Volante",
        "26",
        "Al-Sadd SC"
    ],
    "13": [
        "-",
        "Jassem Gaber Abdulsallam",
        "Volante",
        "20",
        "Al-Arabi SC"
    ],
    "14": [
        "-",
        "Abdulaziz Hatem",
        "Meia Central",
        "31",
        "Al-Rayyan SC"
    ],
    "15": [
        "-",
        "Ahmed Fathi",
        "Meia Central",
        "28",
        "Al-Arabi SC"
    ],
    "16": [
        "-",
        "Ahmad Doozandeh",
        "Meia Central",
        "26",
        "Qatar SC"
    ],
    "17": [
        "-",
        "Abdullah Marafee",
        "Meia Central",
        "30",
        "Al-Arabi SC"
    ],
    "18": [
        "4",
        "Mohammed Waad",
        "Meia Central",
        "22",
        "Al-Sadd SC"
    ],
    "19": [
        "22",
        "Abdullah Al-Ahrak",
        "Meia Ofensivo",
        "24",
        "Al-Sadd SC"
    ],
    "20": [
        "22",
        "Meshaal Barsham",
        "Goleiro",
        "24",
        "Al-Sadd SC"
    ],
    "21": [
        "22",
        "Meshaal Barsham",
        "Goleiro",
        "24",
        "Al-Sadd SC"
    ],
    "22": [
        "22",
        "Meshaal Barsham",
        "Goleiro",
        "24",
        "Al-Sadd SC"
    ],
    "23": [
        "22",
        "Meshaal Barsham",
        "Goleiro",
        "24",
        "Al-Sadd SC"
    ]
  },
  "Canadá": {
    "grupo": "F",
    "Nome": "da Canadá",
    "Treinador": "Treinador",
    "flag": "assets/images/GrupoF/canadá/canadá.png",
    "0": [
        "22",
        "Meshaal Barsham",
        "Goleiro",
        "24",
        "Al-Sadd SC"
    ],
    "1": [
        "1",
        "Saad Al-Sheeb",
        "Goleiro",
        "32",
        "Al-Sadd SC"
    ],
    "2": [
        "21",
        "Yousef Hassan",
        "Goleiro",
        "25",
        "Al-Gharafa SC"
    ],
    "3": [
        "2",
        "Pedro Miguel",
        "Zagueiro",
        "31",
        "Al-Sadd SC"
    ],
    "4": [
        "5",
        "Tarek Salman",
        "Zagueiro",
        "31",
        "Al-Sadd SC"
    ],
    "5": [
        "15",
        "Bassam Al-Rawi",
        "Zagueiro",
        "24",
        "Al-Duhail SC"
    ],
    "6": [
        "16",
        "Boualem Khoukhi",
        "Zagueiro",
        "31",
        "Al-Sadd SC"
    ],
    "7": [
        "3",
        "Abdelkarim Hassan",
        "Lateral Esq.",
        "28",
        "Al-Sadd SC"
    ],
    "8": [
        "24",
        "Homam Ahmed",
        "Lateral Esq.",
        "22",
        "Al-Gharafa SC"
    ],
    "9": [
        "13",
        "Musab Khoder",
        "Lateral Dir.",
        "29",
        "Al-Sadd SC"
    ],
    "10": [
        "12",
        "Karim Boudiaf",
        "Volante",
        "31",
        "Al-Duhail SC"
    ],
    "11": [
        "23",
        "Assim Madibo",
        "Volante",
        "25",
        "Al-Duhail SC"
    ],
    "12": [
        "-",
        "Salem Al-Hajri",
        "Volante",
        "26",
        "Al-Sadd SC"
    ],
    "13": [
        "-",
        "Jassem Gaber Abdulsallam",
        "Volante",
        "20",
        "Al-Arabi SC"
    ],
    "14": [
        "-",
        "Abdulaziz Hatem",
        "Meia Central",
        "31",
        "Al-Rayyan SC"
    ],
    "15": [
        "-",
        "Ahmed Fathi",
        "Meia Central",
        "28",
        "Al-Arabi SC"
    ],
    "16": [
        "-",
        "Ahmad Doozandeh",
        "Meia Central",
        "26",
        "Qatar SC"
    ],
    "17": [
        "-",
        "Abdullah Marafee",
        "Meia Central",
        "30",
        "Al-Arabi SC"
    ],
    "18": [
        "4",
        "Mohammed Waad",
        "Meia Central",
        "22",
        "Al-Sadd SC"
    ],
    "19": [
        "22",
        "Abdullah Al-Ahrak",
        "Meia Ofensivo",
        "24",
        "Al-Sadd SC"
    ],
    "20": [
        "22",
        "Meshaal Barsham",
        "Goleiro",
        "24",
        "Al-Sadd SC"
    ],
    "21": [
        "22",
        "Meshaal Barsham",
        "Goleiro",
        "24",
        "Al-Sadd SC"
    ],
    "22": [
        "22",
        "Meshaal Barsham",
        "Goleiro",
        "24",
        "Al-Sadd SC"
    ],
    "23": [
        "22",
        "Meshaal Barsham",
        "Goleiro",
        "24",
        "Al-Sadd SC"
    ]
  },
  "Marrocos": {
    "grupo": "F",
    "Nome": "do Marrocos",
    "Treinador": "Treinador",
    "flag": "assets/images/GrupoF/marrocos/marrocos.png",
    "0": [
        "22",
        "Meshaal Barsham",
        "Goleiro",
        "24",
        "Al-Sadd SC"
    ],
    "1": [
        "1",
        "Saad Al-Sheeb",
        "Goleiro",
        "32",
        "Al-Sadd SC"
    ],
    "2": [
        "21",
        "Yousef Hassan",
        "Goleiro",
        "25",
        "Al-Gharafa SC"
    ],
    "3": [
        "2",
        "Pedro Miguel",
        "Zagueiro",
        "31",
        "Al-Sadd SC"
    ],
    "4": [
        "5",
        "Tarek Salman",
        "Zagueiro",
        "31",
        "Al-Sadd SC"
    ],
    "5": [
        "15",
        "Bassam Al-Rawi",
        "Zagueiro",
        "24",
        "Al-Duhail SC"
    ],
    "6": [
        "16",
        "Boualem Khoukhi",
        "Zagueiro",
        "31",
        "Al-Sadd SC"
    ],
    "7": [
        "3",
        "Abdelkarim Hassan",
        "Lateral Esq.",
        "28",
        "Al-Sadd SC"
    ],
    "8": [
        "24",
        "Homam Ahmed",
        "Lateral Esq.",
        "22",
        "Al-Gharafa SC"
    ],
    "9": [
        "13",
        "Musab Khoder",
        "Lateral Dir.",
        "29",
        "Al-Sadd SC"
    ],
    "10": [
        "12",
        "Karim Boudiaf",
        "Volante",
        "31",
        "Al-Duhail SC"
    ],
    "11": [
        "23",
        "Assim Madibo",
        "Volante",
        "25",
        "Al-Duhail SC"
    ],
    "12": [
        "-",
        "Salem Al-Hajri",
        "Volante",
        "26",
        "Al-Sadd SC"
    ],
    "13": [
        "-",
        "Jassem Gaber Abdulsallam",
        "Volante",
        "20",
        "Al-Arabi SC"
    ],
    "14": [
        "-",
        "Abdulaziz Hatem",
        "Meia Central",
        "31",
        "Al-Rayyan SC"
    ],
    "15": [
        "-",
        "Ahmed Fathi",
        "Meia Central",
        "28",
        "Al-Arabi SC"
    ],
    "16": [
        "-",
        "Ahmad Doozandeh",
        "Meia Central",
        "26",
        "Qatar SC"
    ],
    "17": [
        "-",
        "Abdullah Marafee",
        "Meia Central",
        "30",
        "Al-Arabi SC"
    ],
    "18": [
        "4",
        "Mohammed Waad",
        "Meia Central",
        "22",
        "Al-Sadd SC"
    ],
    "19": [
        "22",
        "Abdullah Al-Ahrak",
        "Meia Ofensivo",
        "24",
        "Al-Sadd SC"
    ],
    "20": [
        "22",
        "Meshaal Barsham",
        "Goleiro",
        "24",
        "Al-Sadd SC"
    ],
    "21": [
        "22",
        "Meshaal Barsham",
        "Goleiro",
        "24",
        "Al-Sadd SC"
    ],
    "22": [
        "22",
        "Meshaal Barsham",
        "Goleiro",
        "24",
        "Al-Sadd SC"
    ],
    "23": [
        "22",
        "Meshaal Barsham",
        "Goleiro",
        "24",
        "Al-Sadd SC"
    ]
  },
  "Croácia": {
    "grupo": "F",
    "Nome": "da Croácia",
    "Treinador": "Treinador",
    "flag": "assets/images/GrupoF/croácia/croácia.png",
    "0": [
        "22",
        "Meshaal Barsham",
        "Goleiro",
        "24",
        "Al-Sadd SC"
    ],
    "1": [
        "1",
        "Saad Al-Sheeb",
        "Goleiro",
        "32",
        "Al-Sadd SC"
    ],
    "2": [
        "21",
        "Yousef Hassan",
        "Goleiro",
        "25",
        "Al-Gharafa SC"
    ],
    "3": [
        "2",
        "Pedro Miguel",
        "Zagueiro",
        "31",
        "Al-Sadd SC"
    ],
    "4": [
        "5",
        "Tarek Salman",
        "Zagueiro",
        "31",
        "Al-Sadd SC"
    ],
    "5": [
        "15",
        "Bassam Al-Rawi",
        "Zagueiro",
        "24",
        "Al-Duhail SC"
    ],
    "6": [
        "16",
        "Boualem Khoukhi",
        "Zagueiro",
        "31",
        "Al-Sadd SC"
    ],
    "7": [
        "3",
        "Abdelkarim Hassan",
        "Lateral Esq.",
        "28",
        "Al-Sadd SC"
    ],
    "8": [
        "24",
        "Homam Ahmed",
        "Lateral Esq.",
        "22",
        "Al-Gharafa SC"
    ],
    "9": [
        "13",
        "Musab Khoder",
        "Lateral Dir.",
        "29",
        "Al-Sadd SC"
    ],
    "10": [
        "12",
        "Karim Boudiaf",
        "Volante",
        "31",
        "Al-Duhail SC"
    ],
    "11": [
        "23",
        "Assim Madibo",
        "Volante",
        "25",
        "Al-Duhail SC"
    ],
    "12": [
        "-",
        "Salem Al-Hajri",
        "Volante",
        "26",
        "Al-Sadd SC"
    ],
    "13": [
        "-",
        "Jassem Gaber Abdulsallam",
        "Volante",
        "20",
        "Al-Arabi SC"
    ],
    "14": [
        "-",
        "Abdulaziz Hatem",
        "Meia Central",
        "31",
        "Al-Rayyan SC"
    ],
    "15": [
        "-",
        "Ahmed Fathi",
        "Meia Central",
        "28",
        "Al-Arabi SC"
    ],
    "16": [
        "-",
        "Ahmad Doozandeh",
        "Meia Central",
        "26",
        "Qatar SC"
    ],
    "17": [
        "-",
        "Abdullah Marafee",
        "Meia Central",
        "30",
        "Al-Arabi SC"
    ],
    "18": [
        "4",
        "Mohammed Waad",
        "Meia Central",
        "22",
        "Al-Sadd SC"
    ],
    "19": [
        "22",
        "Abdullah Al-Ahrak",
        "Meia Ofensivo",
        "24",
        "Al-Sadd SC"
    ],
    "20": [
        "22",
        "Meshaal Barsham",
        "Goleiro",
        "24",
        "Al-Sadd SC"
    ],
    "21": [
        "22",
        "Meshaal Barsham",
        "Goleiro",
        "24",
        "Al-Sadd SC"
    ],
    "22": [
        "22",
        "Meshaal Barsham",
        "Goleiro",
        "24",
        "Al-Sadd SC"
    ],
    "23": [
        "22",
        "Meshaal Barsham",
        "Goleiro",
        "24",
        "Al-Sadd SC"
    ]
  },
  "Brasil": {
    "grupo": "G",
    "Nome": "do Brasil",
    "Treinador": "Treinador",
    "flag": "assets/images/GrupoG/brasil/brasil.png",
    "0": [
        "22",
        "Meshaal Barsham",
        "Goleiro",
        "24",
        "Al-Sadd SC"
    ],
    "1": [
        "1",
        "Saad Al-Sheeb",
        "Goleiro",
        "32",
        "Al-Sadd SC"
    ],
    "2": [
        "21",
        "Yousef Hassan",
        "Goleiro",
        "25",
        "Al-Gharafa SC"
    ],
    "3": [
        "2",
        "Pedro Miguel",
        "Zagueiro",
        "31",
        "Al-Sadd SC"
    ],
    "4": [
        "5",
        "Tarek Salman",
        "Zagueiro",
        "31",
        "Al-Sadd SC"
    ],
    "5": [
        "15",
        "Bassam Al-Rawi",
        "Zagueiro",
        "24",
        "Al-Duhail SC"
    ],
    "6": [
        "16",
        "Boualem Khoukhi",
        "Zagueiro",
        "31",
        "Al-Sadd SC"
    ],
    "7": [
        "3",
        "Abdelkarim Hassan",
        "Lateral Esq.",
        "28",
        "Al-Sadd SC"
    ],
    "8": [
        "24",
        "Homam Ahmed",
        "Lateral Esq.",
        "22",
        "Al-Gharafa SC"
    ],
    "9": [
        "13",
        "Musab Khoder",
        "Lateral Dir.",
        "29",
        "Al-Sadd SC"
    ],
    "10": [
        "12",
        "Karim Boudiaf",
        "Volante",
        "31",
        "Al-Duhail SC"
    ],
    "11": [
        "23",
        "Assim Madibo",
        "Volante",
        "25",
        "Al-Duhail SC"
    ],
    "12": [
        "-",
        "Salem Al-Hajri",
        "Volante",
        "26",
        "Al-Sadd SC"
    ],
    "13": [
        "-",
        "Jassem Gaber Abdulsallam",
        "Volante",
        "20",
        "Al-Arabi SC"
    ],
    "14": [
        "-",
        "Abdulaziz Hatem",
        "Meia Central",
        "31",
        "Al-Rayyan SC"
    ],
    "15": [
        "-",
        "Ahmed Fathi",
        "Meia Central",
        "28",
        "Al-Arabi SC"
    ],
    "16": [
        "-",
        "Ahmad Doozandeh",
        "Meia Central",
        "26",
        "Qatar SC"
    ],
    "17": [
        "-",
        "Abdullah Marafee",
        "Meia Central",
        "30",
        "Al-Arabi SC"
    ],
    "18": [
        "4",
        "Mohammed Waad",
        "Meia Central",
        "22",
        "Al-Sadd SC"
    ],
    "19": [
        "22",
        "Abdullah Al-Ahrak",
        "Meia Ofensivo",
        "24",
        "Al-Sadd SC"
    ],
    "20": [
        "22",
        "Meshaal Barsham",
        "Goleiro",
        "24",
        "Al-Sadd SC"
    ],
    "21": [
        "22",
        "Meshaal Barsham",
        "Goleiro",
        "24",
        "Al-Sadd SC"
    ],
    "22": [
        "22",
        "Meshaal Barsham",
        "Goleiro",
        "24",
        "Al-Sadd SC"
    ],
    "23": [
        "22",
        "Meshaal Barsham",
        "Goleiro",
        "24",
        "Al-Sadd SC"
    ]
  },
  "Sérvia": {
    "grupo": "G",
    "Nome": "da Sérvia",
    "Treinador": "Treinador",
    "flag": "assets/images/GrupoG/sérvia/sérvia.png",
    "0": [
        "22",
        "Meshaal Barsham",
        "Goleiro",
        "24",
        "Al-Sadd SC"
    ],
    "1": [
        "1",
        "Saad Al-Sheeb",
        "Goleiro",
        "32",
        "Al-Sadd SC"
    ],
    "2": [
        "21",
        "Yousef Hassan",
        "Goleiro",
        "25",
        "Al-Gharafa SC"
    ],
    "3": [
        "2",
        "Pedro Miguel",
        "Zagueiro",
        "31",
        "Al-Sadd SC"
    ],
    "4": [
        "5",
        "Tarek Salman",
        "Zagueiro",
        "31",
        "Al-Sadd SC"
    ],
    "5": [
        "15",
        "Bassam Al-Rawi",
        "Zagueiro",
        "24",
        "Al-Duhail SC"
    ],
    "6": [
        "16",
        "Boualem Khoukhi",
        "Zagueiro",
        "31",
        "Al-Sadd SC"
    ],
    "7": [
        "3",
        "Abdelkarim Hassan",
        "Lateral Esq.",
        "28",
        "Al-Sadd SC"
    ],
    "8": [
        "24",
        "Homam Ahmed",
        "Lateral Esq.",
        "22",
        "Al-Gharafa SC"
    ],
    "9": [
        "13",
        "Musab Khoder",
        "Lateral Dir.",
        "29",
        "Al-Sadd SC"
    ],
    "10": [
        "12",
        "Karim Boudiaf",
        "Volante",
        "31",
        "Al-Duhail SC"
    ],
    "11": [
        "23",
        "Assim Madibo",
        "Volante",
        "25",
        "Al-Duhail SC"
    ],
    "12": [
        "-",
        "Salem Al-Hajri",
        "Volante",
        "26",
        "Al-Sadd SC"
    ],
    "13": [
        "-",
        "Jassem Gaber Abdulsallam",
        "Volante",
        "20",
        "Al-Arabi SC"
    ],
    "14": [
        "-",
        "Abdulaziz Hatem",
        "Meia Central",
        "31",
        "Al-Rayyan SC"
    ],
    "15": [
        "-",
        "Ahmed Fathi",
        "Meia Central",
        "28",
        "Al-Arabi SC"
    ],
    "16": [
        "-",
        "Ahmad Doozandeh",
        "Meia Central",
        "26",
        "Qatar SC"
    ],
    "17": [
        "-",
        "Abdullah Marafee",
        "Meia Central",
        "30",
        "Al-Arabi SC"
    ],
    "18": [
        "4",
        "Mohammed Waad",
        "Meia Central",
        "22",
        "Al-Sadd SC"
    ],
    "19": [
        "22",
        "Abdullah Al-Ahrak",
        "Meia Ofensivo",
        "24",
        "Al-Sadd SC"
    ],
    "20": [
        "22",
        "Meshaal Barsham",
        "Goleiro",
        "24",
        "Al-Sadd SC"
    ],
    "21": [
        "22",
        "Meshaal Barsham",
        "Goleiro",
        "24",
        "Al-Sadd SC"
    ],
    "22": [
        "22",
        "Meshaal Barsham",
        "Goleiro",
        "24",
        "Al-Sadd SC"
    ],
    "23": [
        "22",
        "Meshaal Barsham",
        "Goleiro",
        "24",
        "Al-Sadd SC"
    ]
  },
  "Suíça": {
    "grupo": "G",
    "Nome": "da Suíça",
    "Treinador": "Treinador",
    "flag": "assets/images/GrupoG/suíça/suíça.png",
    "0": [
        "22",
        "Meshaal Barsham",
        "Goleiro",
        "24",
        "Al-Sadd SC"
    ],
    "1": [
        "1",
        "Saad Al-Sheeb",
        "Goleiro",
        "32",
        "Al-Sadd SC"
    ],
    "2": [
        "21",
        "Yousef Hassan",
        "Goleiro",
        "25",
        "Al-Gharafa SC"
    ],
    "3": [
        "2",
        "Pedro Miguel",
        "Zagueiro",
        "31",
        "Al-Sadd SC"
    ],
    "4": [
        "5",
        "Tarek Salman",
        "Zagueiro",
        "31",
        "Al-Sadd SC"
    ],
    "5": [
        "15",
        "Bassam Al-Rawi",
        "Zagueiro",
        "24",
        "Al-Duhail SC"
    ],
    "6": [
        "16",
        "Boualem Khoukhi",
        "Zagueiro",
        "31",
        "Al-Sadd SC"
    ],
    "7": [
        "3",
        "Abdelkarim Hassan",
        "Lateral Esq.",
        "28",
        "Al-Sadd SC"
    ],
    "8": [
        "24",
        "Homam Ahmed",
        "Lateral Esq.",
        "22",
        "Al-Gharafa SC"
    ],
    "9": [
        "13",
        "Musab Khoder",
        "Lateral Dir.",
        "29",
        "Al-Sadd SC"
    ],
    "10": [
        "12",
        "Karim Boudiaf",
        "Volante",
        "31",
        "Al-Duhail SC"
    ],
    "11": [
        "23",
        "Assim Madibo",
        "Volante",
        "25",
        "Al-Duhail SC"
    ],
    "12": [
        "-",
        "Salem Al-Hajri",
        "Volante",
        "26",
        "Al-Sadd SC"
    ],
    "13": [
        "-",
        "Jassem Gaber Abdulsallam",
        "Volante",
        "20",
        "Al-Arabi SC"
    ],
    "14": [
        "-",
        "Abdulaziz Hatem",
        "Meia Central",
        "31",
        "Al-Rayyan SC"
    ],
    "15": [
        "-",
        "Ahmed Fathi",
        "Meia Central",
        "28",
        "Al-Arabi SC"
    ],
    "16": [
        "-",
        "Ahmad Doozandeh",
        "Meia Central",
        "26",
        "Qatar SC"
    ],
    "17": [
        "-",
        "Abdullah Marafee",
        "Meia Central",
        "30",
        "Al-Arabi SC"
    ],
    "18": [
        "4",
        "Mohammed Waad",
        "Meia Central",
        "22",
        "Al-Sadd SC"
    ],
    "19": [
        "22",
        "Abdullah Al-Ahrak",
        "Meia Ofensivo",
        "24",
        "Al-Sadd SC"
    ],
    "20": [
        "22",
        "Meshaal Barsham",
        "Goleiro",
        "24",
        "Al-Sadd SC"
    ],
    "21": [
        "22",
        "Meshaal Barsham",
        "Goleiro",
        "24",
        "Al-Sadd SC"
    ],
    "22": [
        "22",
        "Meshaal Barsham",
        "Goleiro",
        "24",
        "Al-Sadd SC"
    ],
    "23": [
        "22",
        "Meshaal Barsham",
        "Goleiro",
        "24",
        "Al-Sadd SC"
    ]
  },
  "Camarões": {
    "grupo": "G",
    "Nome": "de Camarões",
    "Treinador": "Treinador",
    "flag": "assets/images/GrupoG/camarões/camarões.png",
    "0": [
        "22",
        "Meshaal Barsham",
        "Goleiro",
        "24",
        "Al-Sadd SC"
    ],
    "1": [
        "1",
        "Saad Al-Sheeb",
        "Goleiro",
        "32",
        "Al-Sadd SC"
    ],
    "2": [
        "21",
        "Yousef Hassan",
        "Goleiro",
        "25",
        "Al-Gharafa SC"
    ],
    "3": [
        "2",
        "Pedro Miguel",
        "Zagueiro",
        "31",
        "Al-Sadd SC"
    ],
    "4": [
        "5",
        "Tarek Salman",
        "Zagueiro",
        "31",
        "Al-Sadd SC"
    ],
    "5": [
        "15",
        "Bassam Al-Rawi",
        "Zagueiro",
        "24",
        "Al-Duhail SC"
    ],
    "6": [
        "16",
        "Boualem Khoukhi",
        "Zagueiro",
        "31",
        "Al-Sadd SC"
    ],
    "7": [
        "3",
        "Abdelkarim Hassan",
        "Lateral Esq.",
        "28",
        "Al-Sadd SC"
    ],
    "8": [
        "24",
        "Homam Ahmed",
        "Lateral Esq.",
        "22",
        "Al-Gharafa SC"
    ],
    "9": [
        "13",
        "Musab Khoder",
        "Lateral Dir.",
        "29",
        "Al-Sadd SC"
    ],
    "10": [
        "12",
        "Karim Boudiaf",
        "Volante",
        "31",
        "Al-Duhail SC"
    ],
    "11": [
        "23",
        "Assim Madibo",
        "Volante",
        "25",
        "Al-Duhail SC"
    ],
    "12": [
        "-",
        "Salem Al-Hajri",
        "Volante",
        "26",
        "Al-Sadd SC"
    ],
    "13": [
        "-",
        "Jassem Gaber Abdulsallam",
        "Volante",
        "20",
        "Al-Arabi SC"
    ],
    "14": [
        "-",
        "Abdulaziz Hatem",
        "Meia Central",
        "31",
        "Al-Rayyan SC"
    ],
    "15": [
        "-",
        "Ahmed Fathi",
        "Meia Central",
        "28",
        "Al-Arabi SC"
    ],
    "16": [
        "-",
        "Ahmad Doozandeh",
        "Meia Central",
        "26",
        "Qatar SC"
    ],
    "17": [
        "-",
        "Abdullah Marafee",
        "Meia Central",
        "30",
        "Al-Arabi SC"
    ],
    "18": [
        "4",
        "Mohammed Waad",
        "Meia Central",
        "22",
        "Al-Sadd SC"
    ],
    "19": [
        "22",
        "Abdullah Al-Ahrak",
        "Meia Ofensivo",
        "24",
        "Al-Sadd SC"
    ],
    "20": [
        "22",
        "Meshaal Barsham",
        "Goleiro",
        "24",
        "Al-Sadd SC"
    ],
    "21": [
        "22",
        "Meshaal Barsham",
        "Goleiro",
        "24",
        "Al-Sadd SC"
    ],
    "22": [
        "22",
        "Meshaal Barsham",
        "Goleiro",
        "24",
        "Al-Sadd SC"
    ],
    "23": [
        "22",
        "Meshaal Barsham",
        "Goleiro",
        "24",
        "Al-Sadd SC"
    ]
  },
  "Portugal": {
    "grupo": "H",
    "Nome": "de Portugal",
    "Treinador": "Treinador",
    "flag": "assets/images/GrupoH/portugal/portugal.png",
    "0": [
        "22",
        "Meshaal Barsham",
        "Goleiro",
        "24",
        "Al-Sadd SC"
    ],
    "1": [
        "1",
        "Saad Al-Sheeb",
        "Goleiro",
        "32",
        "Al-Sadd SC"
    ],
    "2": [
        "21",
        "Yousef Hassan",
        "Goleiro",
        "25",
        "Al-Gharafa SC"
    ],
    "3": [
        "2",
        "Pedro Miguel",
        "Zagueiro",
        "31",
        "Al-Sadd SC"
    ],
    "4": [
        "5",
        "Tarek Salman",
        "Zagueiro",
        "31",
        "Al-Sadd SC"
    ],
    "5": [
        "15",
        "Bassam Al-Rawi",
        "Zagueiro",
        "24",
        "Al-Duhail SC"
    ],
    "6": [
        "16",
        "Boualem Khoukhi",
        "Zagueiro",
        "31",
        "Al-Sadd SC"
    ],
    "7": [
        "3",
        "Abdelkarim Hassan",
        "Lateral Esq.",
        "28",
        "Al-Sadd SC"
    ],
    "8": [
        "24",
        "Homam Ahmed",
        "Lateral Esq.",
        "22",
        "Al-Gharafa SC"
    ],
    "9": [
        "13",
        "Musab Khoder",
        "Lateral Dir.",
        "29",
        "Al-Sadd SC"
    ],
    "10": [
        "12",
        "Karim Boudiaf",
        "Volante",
        "31",
        "Al-Duhail SC"
    ],
    "11": [
        "23",
        "Assim Madibo",
        "Volante",
        "25",
        "Al-Duhail SC"
    ],
    "12": [
        "-",
        "Salem Al-Hajri",
        "Volante",
        "26",
        "Al-Sadd SC"
    ],
    "13": [
        "-",
        "Jassem Gaber Abdulsallam",
        "Volante",
        "20",
        "Al-Arabi SC"
    ],
    "14": [
        "-",
        "Abdulaziz Hatem",
        "Meia Central",
        "31",
        "Al-Rayyan SC"
    ],
    "15": [
        "-",
        "Ahmed Fathi",
        "Meia Central",
        "28",
        "Al-Arabi SC"
    ],
    "16": [
        "-",
        "Ahmad Doozandeh",
        "Meia Central",
        "26",
        "Qatar SC"
    ],
    "17": [
        "-",
        "Abdullah Marafee",
        "Meia Central",
        "30",
        "Al-Arabi SC"
    ],
    "18": [
        "4",
        "Mohammed Waad",
        "Meia Central",
        "22",
        "Al-Sadd SC"
    ],
    "19": [
        "22",
        "Abdullah Al-Ahrak",
        "Meia Ofensivo",
        "24",
        "Al-Sadd SC"
    ],
    "20": [
        "22",
        "Meshaal Barsham",
        "Goleiro",
        "24",
        "Al-Sadd SC"
    ],
    "21": [
        "22",
        "Meshaal Barsham",
        "Goleiro",
        "24",
        "Al-Sadd SC"
    ],
    "22": [
        "22",
        "Meshaal Barsham",
        "Goleiro",
        "24",
        "Al-Sadd SC"
    ],
    "23": [
        "22",
        "Meshaal Barsham",
        "Goleiro",
        "24",
        "Al-Sadd SC"
    ]
  },
  "Gana": {
    "grupo": "H",
    "Nome": "de Gana",
    "Treinador": "Treinador",
    "flag": "assets/images/GrupoH/gana/gana.png",
    "0": [
        "22",
        "Meshaal Barsham",
        "Goleiro",
        "24",
        "Al-Sadd SC"
    ],
    "1": [
        "1",
        "Saad Al-Sheeb",
        "Goleiro",
        "32",
        "Al-Sadd SC"
    ],
    "2": [
        "21",
        "Yousef Hassan",
        "Goleiro",
        "25",
        "Al-Gharafa SC"
    ],
    "3": [
        "2",
        "Pedro Miguel",
        "Zagueiro",
        "31",
        "Al-Sadd SC"
    ],
    "4": [
        "5",
        "Tarek Salman",
        "Zagueiro",
        "31",
        "Al-Sadd SC"
    ],
    "5": [
        "15",
        "Bassam Al-Rawi",
        "Zagueiro",
        "24",
        "Al-Duhail SC"
    ],
    "6": [
        "16",
        "Boualem Khoukhi",
        "Zagueiro",
        "31",
        "Al-Sadd SC"
    ],
    "7": [
        "3",
        "Abdelkarim Hassan",
        "Lateral Esq.",
        "28",
        "Al-Sadd SC"
    ],
    "8": [
        "24",
        "Homam Ahmed",
        "Lateral Esq.",
        "22",
        "Al-Gharafa SC"
    ],
    "9": [
        "13",
        "Musab Khoder",
        "Lateral Dir.",
        "29",
        "Al-Sadd SC"
    ],
    "10": [
        "12",
        "Karim Boudiaf",
        "Volante",
        "31",
        "Al-Duhail SC"
    ],
    "11": [
        "23",
        "Assim Madibo",
        "Volante",
        "25",
        "Al-Duhail SC"
    ],
    "12": [
        "-",
        "Salem Al-Hajri",
        "Volante",
        "26",
        "Al-Sadd SC"
    ],
    "13": [
        "-",
        "Jassem Gaber Abdulsallam",
        "Volante",
        "20",
        "Al-Arabi SC"
    ],
    "14": [
        "-",
        "Abdulaziz Hatem",
        "Meia Central",
        "31",
        "Al-Rayyan SC"
    ],
    "15": [
        "-",
        "Ahmed Fathi",
        "Meia Central",
        "28",
        "Al-Arabi SC"
    ],
    "16": [
        "-",
        "Ahmad Doozandeh",
        "Meia Central",
        "26",
        "Qatar SC"
    ],
    "17": [
        "-",
        "Abdullah Marafee",
        "Meia Central",
        "30",
        "Al-Arabi SC"
    ],
    "18": [
        "4",
        "Mohammed Waad",
        "Meia Central",
        "22",
        "Al-Sadd SC"
    ],
    "19": [
        "22",
        "Abdullah Al-Ahrak",
        "Meia Ofensivo",
        "24",
        "Al-Sadd SC"
    ],
    "20": [
        "22",
        "Meshaal Barsham",
        "Goleiro",
        "24",
        "Al-Sadd SC"
    ],
    "21": [
        "22",
        "Meshaal Barsham",
        "Goleiro",
        "24",
        "Al-Sadd SC"
    ],
    "22": [
        "22",
        "Meshaal Barsham",
        "Goleiro",
        "24",
        "Al-Sadd SC"
    ],
    "23": [
        "22",
        "Meshaal Barsham",
        "Goleiro",
        "24",
        "Al-Sadd SC"
    ]
  },
  "Uruguai": {
    "grupo": "H",
    "Nome": "do Uruguai",
    "Treinador": "Treinador",
    "flag": "assets/images/GrupoH/uruguai/uruguai.png",
    "0": [
        "22",
        "Meshaal Barsham",
        "Goleiro",
        "24",
        "Al-Sadd SC"
    ],
    "1": [
        "1",
        "Saad Al-Sheeb",
        "Goleiro",
        "32",
        "Al-Sadd SC"
    ],
    "2": [
        "21",
        "Yousef Hassan",
        "Goleiro",
        "25",
        "Al-Gharafa SC"
    ],
    "3": [
        "2",
        "Pedro Miguel",
        "Zagueiro",
        "31",
        "Al-Sadd SC"
    ],
    "4": [
        "5",
        "Tarek Salman",
        "Zagueiro",
        "31",
        "Al-Sadd SC"
    ],
    "5": [
        "15",
        "Bassam Al-Rawi",
        "Zagueiro",
        "24",
        "Al-Duhail SC"
    ],
    "6": [
        "16",
        "Boualem Khoukhi",
        "Zagueiro",
        "31",
        "Al-Sadd SC"
    ],
    "7": [
        "3",
        "Abdelkarim Hassan",
        "Lateral Esq.",
        "28",
        "Al-Sadd SC"
    ],
    "8": [
        "24",
        "Homam Ahmed",
        "Lateral Esq.",
        "22",
        "Al-Gharafa SC"
    ],
    "9": [
        "13",
        "Musab Khoder",
        "Lateral Dir.",
        "29",
        "Al-Sadd SC"
    ],
    "10": [
        "12",
        "Karim Boudiaf",
        "Volante",
        "31",
        "Al-Duhail SC"
    ],
    "11": [
        "23",
        "Assim Madibo",
        "Volante",
        "25",
        "Al-Duhail SC"
    ],
    "12": [
        "-",
        "Salem Al-Hajri",
        "Volante",
        "26",
        "Al-Sadd SC"
    ],
    "13": [
        "-",
        "Jassem Gaber Abdulsallam",
        "Volante",
        "20",
        "Al-Arabi SC"
    ],
    "14": [
        "-",
        "Abdulaziz Hatem",
        "Meia Central",
        "31",
        "Al-Rayyan SC"
    ],
    "15": [
        "-",
        "Ahmed Fathi",
        "Meia Central",
        "28",
        "Al-Arabi SC"
    ],
    "16": [
        "-",
        "Ahmad Doozandeh",
        "Meia Central",
        "26",
        "Qatar SC"
    ],
    "17": [
        "-",
        "Abdullah Marafee",
        "Meia Central",
        "30",
        "Al-Arabi SC"
    ],
    "18": [
        "4",
        "Mohammed Waad",
        "Meia Central",
        "22",
        "Al-Sadd SC"
    ],
    "19": [
        "22",
        "Abdullah Al-Ahrak",
        "Meia Ofensivo",
        "24",
        "Al-Sadd SC"
    ],
    "20": [
        "22",
        "Meshaal Barsham",
        "Goleiro",
        "24",
        "Al-Sadd SC"
    ],
    "21": [
        "22",
        "Meshaal Barsham",
        "Goleiro",
        "24",
        "Al-Sadd SC"
    ],
    "22": [
        "22",
        "Meshaal Barsham",
        "Goleiro",
        "24",
        "Al-Sadd SC"
    ],
    "23": [
        "22",
        "Meshaal Barsham",
        "Goleiro",
        "24",
        "Al-Sadd SC"
    ]
  },
  "Coréia do Sul": {
    "grupo": "H",
    "Nome": "da Coréia do Sul",
    "Treinador": "Treinador",
    "flag": "assets/images/GrupoH/coréia do sul/coréia do sul.png",
    "0": [
        "22",
        "Meshaal Barsham",
        "Goleiro",
        "24",
        "Al-Sadd SC"
    ],
    "1": [
        "1",
        "Saad Al-Sheeb",
        "Goleiro",
        "32",
        "Al-Sadd SC"
    ],
    "2": [
        "21",
        "Yousef Hassan",
        "Goleiro",
        "25",
        "Al-Gharafa SC"
    ],
    "3": [
        "2",
        "Pedro Miguel",
        "Zagueiro",
        "31",
        "Al-Sadd SC"
    ],
    "4": [
        "5",
        "Tarek Salman",
        "Zagueiro",
        "31",
        "Al-Sadd SC"
    ],
    "5": [
        "15",
        "Bassam Al-Rawi",
        "Zagueiro",
        "24",
        "Al-Duhail SC"
    ],
    "6": [
        "16",
        "Boualem Khoukhi",
        "Zagueiro",
        "31",
        "Al-Sadd SC"
    ],
    "7": [
        "3",
        "Abdelkarim Hassan",
        "Lateral Esq.",
        "28",
        "Al-Sadd SC"
    ],
    "8": [
        "24",
        "Homam Ahmed",
        "Lateral Esq.",
        "22",
        "Al-Gharafa SC"
    ],
    "9": [
        "13",
        "Musab Khoder",
        "Lateral Dir.",
        "29",
        "Al-Sadd SC"
    ],
    "10": [
        "12",
        "Karim Boudiaf",
        "Volante",
        "31",
        "Al-Duhail SC"
    ],
    "11": [
        "23",
        "Assim Madibo",
        "Volante",
        "25",
        "Al-Duhail SC"
    ],
    "12": [
        "-",
        "Salem Al-Hajri",
        "Volante",
        "26",
        "Al-Sadd SC"
    ],
    "13": [
        "-",
        "Jassem Gaber Abdulsallam",
        "Volante",
        "20",
        "Al-Arabi SC"
    ],
    "14": [
        "-",
        "Abdulaziz Hatem",
        "Meia Central",
        "31",
        "Al-Rayyan SC"
    ],
    "15": [
        "-",
        "Ahmed Fathi",
        "Meia Central",
        "28",
        "Al-Arabi SC"
    ],
    "16": [
        "-",
        "Ahmad Doozandeh",
        "Meia Central",
        "26",
        "Qatar SC"
    ],
    "17": [
        "-",
        "Abdullah Marafee",
        "Meia Central",
        "30",
        "Al-Arabi SC"
    ],
    "18": [
        "4",
        "Mohammed Waad",
        "Meia Central",
        "22",
        "Al-Sadd SC"
    ],
    "19": [
        "22",
        "Abdullah Al-Ahrak",
        "Meia Ofensivo",
        "24",
        "Al-Sadd SC"
    ],
    "20": [
        "22",
        "Meshaal Barsham",
        "Goleiro",
        "24",
        "Al-Sadd SC"
    ],
    "21": [
        "22",
        "Meshaal Barsham",
        "Goleiro",
        "24",
        "Al-Sadd SC"
    ],
    "22": [
        "22",
        "Meshaal Barsham",
        "Goleiro",
        "24",
        "Al-Sadd SC"
    ],
    "23": [
        "22",
        "Meshaal Barsham",
        "Goleiro",
        "24",
        "Al-Sadd SC"
    ]
  }
}